[{"id": "id", "claim": "claim", "rating": "rating", "image_url": "image_url", "permalink": "permalink(REDDIT)", "publish_date": "publish_date", "keyword": "keyword", "twitter_url": "twitter_url", "null": ["", "", "", ""]}, {"id": "2000", "claim": "MoviePass' parent company says it had a service outage on Thursday because it couldn't afford to pay for movie tickets", "rating": "TRUE", "image_url": "['http://i2.cdn.turner.com/money/dam/assets/171016102155-moviepass-logo-1100x619.jpg']", "permalink": "", "publish_date": "20018-07-27T00:00:00+00:00", "keyword": "MoviePass parent outage afford", "twitter_url": "https://twitter.com/cnnbrk/status/1022867815647338497", "null": ["", "", "", ""]}, {"id": "2001", "claim": "The US economy grew at an annual rate of 4.1% for the second quarter of this year ¡ª the fastest pace since 2014 ", "rating": "TRUE", "image_url": "['https://i2.cdn.turner.com/money/dam/assets/180209075755-02-boeing-factory-washington-1280x720.jpg']", "permalink": "", "publish_date": "20018-07-27T00:00:00+00:01", "keyword": "US economy grew fastest", "twitter_url": "https://twitter.com/cnnbrk/status/1022824920391331840", "null": ["", "", "", ""]}, {"id": "2002", "claim": "North Korea hands over the possible remains of American war dead ", "rating": "TRUE", "image_url": "['https://cdn.cnn.com/cnnnext/dam/assets/180611210012-trump-kim-jong-un-summit-super-169.jpg']", "permalink": "", "publish_date": "20018-07-26T00:00:00+00:02", "keyword": "North Koread US troops", "twitter_url": "https://twitter.com/cnnbrk/status/1022666648879333376", "null": ["", "", "", ""]}, {"id": "2003", "claim": "Hundreds of separated children not reunited by court-ordered deadline", "rating": "TRUE", "image_url": "['https://pbs.twimg.com/media/DjEMMiIUwAAL2AL.jpg']", "permalink": "", "publish_date": "20018-07-26T00:00:00+00:03", "keyword": "separated children reunited court-ordered ", "twitter_url": "https://twitter.com/cnnbrk/status/1022612063829585922", "null": ["", "", "", ""]}, {"id": "2004", "claim": "Trump administration set to help farmers hurt by tariffs", "rating": "TRUE", "image_url": "['https://media1.ledevoir.com/images_galerie/nwd_642328_489666/image.jpg']", "permalink": "", "publish_date": "20018-07-24T00:00:00+00:04", "keyword": "Trump help farmers tariffs", "twitter_url": "https://twitter.com/cnnbrk/status/1021778267735502848", "null": ["", "", "", ""]}, {"id": "2005", "claim": "Americans can legally download 3-D printed guns starting next month", "rating": "TRUE", "image_url": "['https://cdn.theatlantic.com/assets/media/img/mt/2015/05/3D_Gun_1/facebook.jpg?1522840650']", "permalink": "", "publish_date": "20018-07-20T00:00:00+00:05", "keyword": "legally download 3D gun", "twitter_url": "https://twitter.com/cnnbrk/status/1020063714920185857", "null": ["", "", "", ""]}, {"id": "2006", "claim": "Government shuts down website for doctors searching for treatment guidelines", "rating": "TRUE", "image_url": "['https://cdn.cnn.com/cnnnext/dam/assets/180627013115-hhs-seal-super-tease.jpg']", "permalink": "", "publish_date": "20018-07-16T00:00:00+00:06", "keyword": "website down doctors guidelines", "twitter_url": "https://twitter.com/cnnbrk/status/1018976163551694848", "null": ["", "", "", ""]}, {"id": "2007", "claim": "France crowned world champion after 4-2 win over Croatia.", "rating": "TRUE", "image_url": "['https://www.nacion.com/resizer/cmuUrZBmeIZzDwZQ3bTAJBs7swg=/1200x0/center/middle/filters:quality(100)/www.nacion.com/resizer/MCCfHnQI92vYcUz9flbTncvxLIw=/1200x0/center/middle/filters:quality(100)/arc-anglerfish-arc2-prod-gruponacion.s3.amazonaws.com/public/BQ5ZAWUWCVDCDIS6VQIRKCPJGI.jpg']", "permalink": "", "publish_date": "20018-07-15T00:00:00+00:07", "keyword": "Fance champion win Croatia", "twitter_url": "https://twitter.com/cnnbrk/status/1018540020024500224", "null": ["", "", "", ""]}, {"id": "2008", "claim": "Paragliding Trump protester arrested", "rating": "TRUE", "image_url": "['https://cdn.cnn.com/cnnnext/dam/assets/180714094950-anti-trump-paraglider.jpg']", "permalink": "", "publish_date": "20018-07-15T00:00:00+00:08", "keyword": "Paragliding Trump protester arrested", "twitter_url": "https://twitter.com/cnnbrk/status/1018512044079841280", "null": ["", "", "", ""]}, {"id": "2009", "claim": "Eight endangered black rhinos have died after being relocated to a sanctuary in southern Kenya", "rating": "TRUE", "image_url": "['https://cdn.cnn.com/cnnnext/dam/assets/180713112040-kenya-rhino-relocation-1-super-tease.jpg']", "permalink": "", "publish_date": "20018-07-13T00:00:00+00:09", "keyword": "rhinos died relocated sanctuary", "twitter_url": "https://twitter.com/cnnbrk/status/1017833586265853953", "null": ["", "", "", ""]}, {"id": "2010", "claim": "More than 100 people in Illinois and Iowa are ill from a parasite possibly linked to McDonald's salads", "rating": "TRUE", "image_url": "['https://cdn.cnn.com/cnnnext/dam/assets/120821025442-mcdonalds-golden-arches-super-169.jpg']", "permalink": "", "publish_date": "20018-07-27T00:00:00+00:10", "keyword": "ill parasite McDonald", "twitter_url": "https://twitter.com/cnnbrk/status/1017593779346341890", "null": ["", "", "", ""]}, {"id": "2011", "claim": "NFL player's union files grievance against national anthem policy", "rating": "TRUE", "image_url": "['https://cdn.cnn.com/cnnnext/dam/assets/180607170738-02-nfl-kneel-anthem-protest-file-full-169.jpg']", "permalink": "", "publish_date": "20018-07-10T00:00:00+00:11", "keyword": "NFL grievance against anthem ", "twitter_url": "https://twitter.com/cnnbrk/status/1016741178786672642", "null": ["", "", "", ""]}, {"id": "2012", "claim": "Rescuers up against 'water and time' to save remaining teammates trapped in Thai cave", "rating": "TRUE", "image_url": "['https://i1.wp.com/ifooh.com/wp-content/uploads/2018/07/636666494184236284-AFP-AFP-17A8IV.jpg?fit=3200%2C1680&ssl=1']", "permalink": "", "publish_date": "20018-07-08T00:00:00+00:12", "keyword": "rescuers  trapped Thai cave", "twitter_url": "https://twitter.com/cnnbrk/status/1015939227480141824", "null": ["", "", "", ""]}, {"id": "2013", "claim": "Croatia defeats host Russia in World Cup penalty shootout", "rating": "TRUE", "image_url": "['https://cdn.cnn.com/cnnnext/dam/assets/180707212050-vida-super-168.jpg']", "permalink": "", "publish_date": "20018-07-07T00:00:00+00:13", "keyword": "Croatia Russia Cup shootout", "twitter_url": "https://twitter.com/cnnbrk/status/1015704183545057280", "null": ["", "", "", ""]}, {"id": "2014", "claim": "Chicago gun violence protesters close major interstate near downtown", "rating": "TRUE", "image_url": "['https://cdn.cnn.com/cnnnext/dam/assets/180707114018-03-chicago-protests-070718-full-169.jpg']", "permalink": "", "publish_date": "20018-07-07T00:00:00+00:14", "keyword": "Chicago gun protesters interstaet", "twitter_url": "https://twitter.com/cnnbrk/status/1015641782346973184", "null": ["", "", "", ""]}, {"id": "2015", "claim": "North Korea pans 'gangster-like mindset' of US as Pompeo signals 'progress' in talks", "rating": "TRUE", "image_url": "['https://cdn.cnn.com/cnnnext/dam/assets/180706204041-pompeo-north-korea-full-169.jpg ']", "permalink": "", "publish_date": "20018-07-07T00:00:00+00:15", "keyword": "North Koread gangster-like mindset", "twitter_url": "https://twitter.com/cnnbrk/status/1015603845337092097", "null": ["", "", "", " "]}, {"id": "2016", "claim": "A woman climbed the base of the Statue of Liberty on the Fourth of July to protest migrant family separations", "rating": "TRUE", "image_url": "['https://webnews.bg/uploads/images/79/6579/366579/768x432.jpg?_=1530755556']", "permalink": "", "publish_date": "20018-07-27T00:00:00+00:16", "keyword": "climbed Liverty protest migrant ", "twitter_url": "https://twitter.com/cnnbrk/status/1014643265449201664", "null": ["", "", "", ""]}, {"id": "2017", "claim": "Archbishop Wilson convicted of covering up sex abuse avoids prison ", "rating": "TRUE", "image_url": "['https://cdn.cnn.com/cnnnext/dam/assets/180618192442-archbishop-philip-wilson-court-0522-restricted-super-169.jpg']", "permalink": "", "publish_date": "20018-07-04T00:00:00+00:17", "keyword": "Archbishop covering sex avoids", "twitter_url": "https://twitter.com/cnnbrk/status/1013945810227167235", "null": ["", "", "", ""]}, {"id": "2018", "claim": "Liquid water 'lake' revealed on Mars.", "rating": "TRUE", "image_url": "['https://www.newsfirst.lk/sinhala/wp-content/uploads/2018/07/mars.jpg']", "permalink": "", "publish_date": "20018-07-25T00:00:00+00:18", "keyword": "Liquid lake revealed Mars", "twitter_url": "https://twitter.com/BBCBreaking/status/1022125032024297473", "null": ["", "", "", ""]}, {"id": "2019", "claim": "Kit Kat case: No break for Nestl¨¦ in trademark row.", "rating": "TRUE", "image_url": "['http://www.wepress2impress.com/wp-content/uploads/2018/07/kit-kat-case-no-break-for-nestle-in-trademark-row-976x470.jpg']", "permalink": "", "publish_date": "20018-07-25T00:00:00+00:19", "keyword": "Kat break Nestle trademark", "twitter_url": "https://twitter.com/BBCBreaking/status/1022064263161098245", "null": ["", "", "", ""]}, {"id": "2020", "claim": "Worcester 'acid attack': Boy aged three injured", "rating": "TRUE", "image_url": "['https://www.newshub.co.nz/home/world/2018/07/acid-attack-on-british-toddler/_jcr_content/par/video/image.dynimg.full.q75.jpg']", "permalink": "", "publish_date": "20018-07-22T00:00:00+00:20", "keyword": "Worcester acid attack injured", "twitter_url": "https://twitter.com/BBCBreaking/status/1020977914823741440", "null": ["", "", "", ""]}, {"id": "2021", "claim": "German bus knife attack leaves several wounded", "rating": "TRUE", "image_url": "['http://media.alalam.ir/uploads/855x495/153209838528703100.jpg']", "permalink": "", "publish_date": "20018-07-27T00:00:00+00:21", "keyword": "hurt German bus knife", "twitter_url": "https://twitter.com/BBCBreaking/status/1020301041160663040", "null": ["", "", "", ""]}, {"id": "2022", "claim": "Alisson: Liverpool offer for Brazil goalkeeper accepted by Roma", "rating": "TRUE", "image_url": "['https://lh3.googleusercontent.com/-PzbcgTzve40/W0-Ml_2cNzI/AAAAAAAAHW4/aU2GW8rDZfgppRSPEusr9DQu06YvfGxogCHMYCw/s1600/a-96.jpg']", "permalink": "", "publish_date": "20018-07-27T00:00:00+00:22", "keyword": "Alisson Liverpool goalkeeper Roma", "twitter_url": "https://twitter.com/BBCSport/status/1019537161111162880", "null": ["", "", "", ""]}, {"id": "2023", "claim": "Cliff Richard: Singer wins BBC privacy case at High Court", "rating": "TRUE", "image_url": "['http://news.images.itv.com/image/file/1591881/stream_2.37629295.jpg']", "permalink": "", "publish_date": "20018-07-18T00:00:00+00:23", "keyword": "Cliff wins BBC privacy", "twitter_url": "https://twitter.com/BBCBreaking/status/1019518782765707264", "null": ["", "", "", ""]}, {"id": "2024", "claim": "Brexit: Vote Leave broke electoral law, says Electoral Commission", "rating": "TRUE", "image_url": "['https://i2.wp.com/viralords.com/wp-content/uploads/2018/07/c7fb9ff154c4baa56bebe758158959e1.jpeg?fit=1024%2C576&ssl=1']", "permalink": "", "publish_date": "20018-07-17T00:00:00+00:24", "keyword": "Brexit  Vote leave broke ", "twitter_url": "https://twitter.com/BBCBreaking/status/1019103890023813120", "null": ["", "", "", ""]}, {"id": "2025", "claim": "FRANCE ARE THE WORLD CHAMPIONS! ", "rating": "TRUE", "image_url": "['https://static1.squarespace.com/static/5981b7e2197aeacdba971b27/5b4d405088251b46c07ae413/5b4d40fc6d2a734b328a9a19/1531789584415/France-WC-Winners1.png?format=1500w']", "permalink": "", "publish_date": "20018-07-15T00:00:00+00:25", "keyword": "Fance world Champions Final", "twitter_url": "https://twitter.com/BBCSport/status/1018539143100497921", "null": ["", "", "", ""]}, {"id": "2026", "claim": "Belgium overcome England to take third at World Cup", "rating": "TRUE", "image_url": "['https://pbs.twimg.com/media/DiEtalYXkAAeaNe.jpg:large']", "permalink": "", "publish_date": "20018-07-12T00:00:00+00:26", "keyword": "Belgium Englangd third Cup", "twitter_url": "https://twitter.com/BBCSport/status/1018161194446700547", "null": ["", "", "", ""]}, {"id": "2027", "claim": "Murdoch's Fox cleared for Sky takeover bid", "rating": "TRUE", "image_url": "['https://images.radio-canada.ca/v1/ici-premiere/perso/mlarge-rupert-murdoch-magnat-20th-century-fox.jpg']", "permalink": "", "publish_date": "20018-07-27T00:00:00+00:27", "keyword": "Murdoch Fox cleared bid", "twitter_url": "https://twitter.com/BBCBreaking/status/1017370861421105152", "null": ["", "", "", ""]}, {"id": "2028", "claim": "Tory vice-chairs quit over PM's Brexit plan", "rating": "TRUE", "image_url": "['https://www.telegraph.co.uk/content/dam/politics/2018/07/10/TELEMMGLPICT000168858213-xlarge_trans_NvBQzQNjv4Bq-pfgFGBz9L_4V5dRQnfCxd6yN5CV7Pul_xM_LGnPwu0.jpeg']", "permalink": "", "publish_date": "20018-07-10T00:00:00+00:28", "keyword": "Tory vice-chairs qtui Brexit", "twitter_url": "https://twitter.com/BBCBreaking/status/1016711409974042628", "null": ["", "", "", ""]}, {"id": "2029", "claim": "RAF centenary: Thousands watch flypast.", "rating": "TRUE", "image_url": "['https://www.thesun.co.uk/wp-content/uploads/2018/07/NINTCHDBPICT000419408988.jpg?w={width}']", "permalink": "", "publish_date": "20018-07-10T00:00:00+00:29", "keyword": "RAF centenary thousands flypast", "twitter_url": "https://twitter.com/BBCBreaking/status/1016659573011185666", "null": ["", "", "", ""]}, {"id": "2030", "claim": "All 12 boys and their football coach rescued from flooded cave system in Chiang Rai", "rating": "TRUE", "image_url": "['https://www.debate.com.mx/__export/1531584794912/sites/debate/img/2018/07/14/whatsapp_image_2018-07-14_at_08_58_40.jpeg_423682103.jpeg']", "permalink": "", "publish_date": "20018-07-10T00:00:00+00:30", "keyword": "football rescued cave  Chiang ", "twitter_url": "https://twitter.com/BBCBreaking/status/1016651921241853952", "null": ["", "", "", ""]}, {"id": "2031", "claim": "Gun control advocates can't stop group from posting instructions to 3-D print a gun", "rating": "TRUE", "image_url": "['https://firenewsfeed.com/image/728x410/aHR0cHM6Ly9jZG4uY25uLmNvbS9jbm5uZXh0L2RhbS9hc3NldHMvMTQwODE4MTk1ODIwLTNkLXByaW50ZWQtZ3VuLTEyODB4NzIwLXN0b3J5LXRvcC5qcGc=']", "permalink": "", "publish_date": "20018-07-27T00:00:00+00:31", "keyword": "gun stop posting 3-D", "twitter_url": "https://twitter.com/cnnbrk/status/1023022254429532160", "null": ["", "", "", ""]}, {"id": "2032", "claim": "NYPD looking into reports of 3 suspicious packages at Trump Tower", "rating": "TRUE", "image_url": "['https://www.ilmessaggero.it/photos/HIGH/13/99/3881399_0058_trump_tower_pacchi_sospetti.jpg']", "permalink": "", "publish_date": "20018-07-27T00:00:00+00:32", "keyword": "NTPD suspicious Trump Tower", "twitter_url": "https://twitter.com/cnnbrk/status/1022974986561179648", "null": ["", "", "", ""]}, {"id": "2033", "claim": "Civil rights icon Rep. John Lewis hospitalized", "rating": "TRUE", "image_url": "['https://cdn.cnn.com/cnnnext/dam/assets/180307133018-john-lewis-edmund-pettus-bridge-full-169.jpg']", "permalink": "", "publish_date": "20018-07-28T00:00:00+00:33", "keyword": "Civil icon Rep.John hospitalized", "twitter_url": "https://twitter.com/cnnbrk/status/1023425218012950529", "null": ["", "", "", ""]}, {"id": "2034", "claim": "Georgia lawmaker who came under fire after yelling 'n-word' on 'Who Is America?' says he'll quit", "rating": "TRUE", "image_url": "['https://pbs.twimg.com/media/Di8c669XgAANEFe.jpg:large']", "permalink": "", "publish_date": "20018-07-24T00:00:00+00:34", "keyword": "lawmaker dropped trousers n-word", "twitter_url": "https://twitter.com/cnnbrk/status/1023425218012950529", "null": ["", "", "", ""]}, {"id": "2035", "claim": "LeBron James to join Lakers for $154 million over 4 years", "rating": "TRUE", "image_url": "['https://www.nbcsports.com/sites/nbcsports.com/files/2018/06/11/nbc_dps_reggiemilleronlbj_180611.jpg']", "permalink": "", "publish_date": "20018-07-02T00:00:00+00:35", "keyword": "LeBron join Lakers million", "twitter_url": "https://twitter.com/cnnbrk/status/1013583161333309440", "null": ["", "", "", ""]}, {"id": "2036", "claim": "Boise stabbing suspect wanted revenge, police say; 6 kids among injured", "rating": "TRUE", "image_url": "['http://storage.tvanouvelles.ca/v1/dynamic_resize/sws_path/tvanouvelles_prod/1033059e-47ca-4a89-bf04-d7c720ed2ef5_16x9_WEB.jpg?quality=80&size=1200x&version=1']", "permalink": "", "publish_date": "20018-07-01T00:00:00+00:36", "keyword": " Boise stabbing revenge kids", "twitter_url": "https://twitter.com/cnnbrk/status/1013529875024576512", "null": ["", "", "", ""]}, {"id": "2037", "claim": "Canada hits $13 billion of US goods with new tariffs", "rating": "TRUE", "image_url": "['http://espanol24.com/cnnes/wp-content/uploads/2018/07/180628131021-donald-trump-justin-trudeau-us-canada-trade-780x439.jpg']", "permalink": "", "publish_date": "20018-07-01T00:00:00+00:37", "keyword": "Canada hits US tariffs", "twitter_url": "https://twitter.com/cnnbrk/status/1013486173044527107", "null": ["", "", "", ""]}, {"id": "2038", "claim": "Protesters march against Trump's immigration policy", "rating": "TRUE", "image_url": "['https://pbs.twimg.com/media/Dg8gM_NUcAI2dFl.jpg']", "permalink": "", "publish_date": "20018-06-30T00:00:00+00:38", "keyword": "Protesters march Trump's immigration", "twitter_url": "https://twitter.com/cnnbrk/status/1013066328175972355", "null": ["", "", "", ""]}, {"id": "2039", "claim": "GM warns tariff could force job cuts, raise cost of cars ", "rating": "TRUE", "image_url": "['https://www.francetvinfo.fr/image/75e7k1xax-80ce/1500/843/12529756.jpg']", "permalink": "", "publish_date": "20018-06-29T00:00:00+00:39", "keyword": "GM tariff job cuts", "twitter_url": "https://twitter.com/CNNMoney/status/1012798267950845952", "null": ["", "", "", ""]}, {"id": "2040", "claim": "First lady Melania Trump arrives in Arizona for her second trip to immigration facilities", "rating": "TRUE", "image_url": "['https://dynaimage.cdn.cnn.com/cnn/c_fill,g_auto,w_1200,h_675,ar_16:9/https%3A%2F%2Fcdn.cnn.com%2Fcnnnext%2Fdam%2Fassets%2F180628131511-01-melania-trump-arizona-0628.jpg']", "permalink": "", "publish_date": "20018-06-28T00:00:00+00:40", "keyword": "Melania Arizona second immigration", "twitter_url": "https://twitter.com/CNNPolitics/status/1012391958789152769", "null": ["", "", "", ""]}, {"id": "2041", "claim": "Trump casts doubt on Russian election meddling ahead of Putin summit", "rating": "TRUE", "image_url": "['https://pbs.twimg.com/media/DiPGa1yWkAEmCeq.jpg']", "permalink": "", "publish_date": "20018-06-28T00:00:00+00:41", "keyword": "Treump Russian election meddling", "twitter_url": "https://twitter.com/cnnbrk/status/1012310639589646336", "null": ["", "", "", ""]}, {"id": "2042", "claim": "Joe Jackson, musical family patriarch, dead at 89", "rating": "TRUE", "image_url": "['https://cnnespanol2.files.wordpress.com/2018/06/180627115519-joe-jackson-2009-file-full-169.jpg?quality=100&strip=info&w=1200']", "permalink": "", "publish_date": "20018-06-T00:2600:00+00:42", "keyword": "Joe Jackson patriarch dead", "twitter_url": "https://twitter.com/cnnbrk/status/1012011712856449025", "null": ["", "", "", ""]}, {"id": "2043", "claim": "House Intelligence Chairman Devin Nunes is demanding new information on Trump campaign and FBI informants", "rating": "TRUE", "image_url": "['https://cdn.cnn.com/cnnnext/dam/assets/180504124446-devin-nunes-feb-08-super-tease.jpg ']", "permalink": "", "publish_date": "20018-06-26T00:00:00+00:43", "keyword": "Devin Nunes demanding information ", "twitter_url": "https://twitter.com/CNNPolitics/status/1011825233362341889", "null": ["", "", "", ""]}, {"id": "2044", "claim": "Federal judge orders reunification of parents and children, end to most family separations at border", "rating": "TRUE", "image_url": "['https://cnnespanol2.files.wordpress.com/2018/06/180616030010-dhs-family-separation-01-full-169.jpg?quality=100&strip=info&strip=info']", "permalink": "", "publish_date": "20018-06-26T00:00:00+00:44", "keyword": "Federal reunification end separations", "twitter_url": "https://twitter.com/CNNPolitics/status/1011819000513298432", "null": ["", "", "", ""]}, {"id": "2045", "claim": "A 28-year-old Democratic Socialist just ousted a powerful, 10-term congressman in New York ", "rating": "TRUE", "image_url": "['https://cdn.cnn.com/cnnnext/dam/assets/180626124237-aoc-2-super-tease.jpg ']", "permalink": "", "publish_date": "20018-06-27T00:00:00+00:45", "keyword": "28-year-old socialist ousted 10-term", "twitter_url": "https://twitter.com/cnnbrk/status/1011794427973644288", "null": ["", "", "", ""]}, {"id": "2046", "claim": "Sarah Sanders to receive Secret Service protection", "rating": "TRUE", "image_url": "['https://cdn.cnn.com/cnnnext/dam/assets/180605200516-sarah-sanders-ataques-trump-regano-noticias-frase-directa-dusa-00001313-super-tease.jpg ']", "permalink": "", "publish_date": "20018-06-26T00:00:00+00:46", "keyword": "Sarah Sanders receive protection", "twitter_url": "https://twitter.com/cnnbrk/status/1011749396155858944", "null": ["", "", "", ""]}, {"id": "2047", "claim": "Supreme Court upholds travel ban", "rating": "TRUE", "image_url": "['https://cdn.cnn.com/cnnnext/dam/assets/170629201807-01-travel-ban-protest-june-29-2017-super-tease.jpg ']", "permalink": "", "publish_date": "20018-06-26T00:00:00+00:47", "keyword": "Supreme upholds travel ban", "twitter_url": "https://twitter.com/cnnbrk/status/1011621621252214786", "null": ["", "", "", ""]}, {"id": "2048", "claim": "Trump accuses Harley-Davidson of waving 'white flag' in budding trade war", "rating": "TRUE", "image_url": "['https://cdn.cnn.com/cnnnext/dam/assets/180625162423-01-harley-davidson-trump-062518-full-169.jpg ']", "permalink": "", "publish_date": "20018-06-25T00:00:00+00:48", "keyword": "Trump accuses Harley-Davisdon waving", "twitter_url": "https://twitter.com/cnnbrk/status/1011377759606755328", "null": ["", "", "", ""]}, {"id": "2049", "claim": "Pawn Stars' star Richard Harrison, known as 'The Old Man,' dies", "rating": "TRUE", "image_url": "['https://static.independent.co.uk/s3fs-public/thumbnails/image/2018/06/25/16/pawn-stars-1.jpg ']", "permalink": "", "publish_date": "20018-06-25T00:00:00+00:49", "keyword": "Richard Harrison Old dies", "twitter_url": "https://twitter.com/cnnbrk/status/1011313281192079362", "null": ["", "", "", ""]}, {"id": "2050", "claim": "Harley-Davidson will move some production out of the US to avoid EU retaliatory tariffs", "rating": "TRUE", "image_url": "['http://harley-davidson.motowp.com/sportster/forty-eight/2016/Harley-Davidson-Sportster-Forty-Eight-2016-5120x2880-005.jpg ']", "permalink": "", "publish_date": "20018-06-25T00:00:00+00:50", "keyword": "Harley-Davidson move avoid EU", "twitter_url": "https://twitter.com/cnnbrk/status/1011227424099569664", "null": ["", "", "", ""]}, {"id": "2051", "claim": "Teenage boy reported missing from Texas facility that cares for migrants, police say", "rating": "TRUE", "image_url": "['https://cdn.cnn.com/cnnnext/dam/assets/180613213109-02-southwest-key-programs-casa-padre-shelter-exlarge-169.jpg']", "permalink": "", "publish_date": "20018-06-24T00:00:00+00:51", "keyword": "Teenage missing Texas migrants", "twitter_url": "https://twitter.com/cnnbrk/status/1011006498829369344", "null": ["", "", "", ""]}, {"id": "2052", "claim": "Almost 350 migrants are stranded on two boats in the Mediterranean", "rating": "TRUE", "image_url": "['https://cdn.cnn.com/cnnnext/dam/assets/180624084745-03-mission-lifeline-libya-0621-super-tease.jpg ']", "permalink": "", "publish_date": "20018-06-24T00:00:00+00:52", "keyword": "migrants stranded boats Mediterranean", "twitter_url": "https://twitter.com/cnnbrk/status/1010915918950682624", "null": ["", "", "", ""]}, {"id": "2053", "claim": "Trump jabs 'Wacky Jacky and Pocahontas' while campaigning for Dean Heller in Nevada", "rating": "TRUE", "image_url": "['https://cdn.cnn.com/cnnnext/dam/assets/180623154500-01-donald-trump-nevada-0623-screengrab-super-169.jpg']", "permalink": "", "publish_date": "20018-06-23T00:00:00+00:53", "keyword": "Trump jabs Wacky Nevada", "twitter_url": "https://twitter.com/cnnbrk", "null": ["", "", "", ""]}, {"id": "2054", "claim": "Women in Saudi Arabia can now drive legally for the first time", "rating": "TRUE", "image_url": "['https://pbs.twimg.com/media/DgZ6aCIU0AET8Ds.jpg ']", "permalink": "", "publish_date": "20018-06-23T00:00:00+00:54", "keyword": "Arabia drive legally first", "twitter_url": "https://twitter.com/cnnbrk/status/1010629878264287232", "null": ["", "", "", ""]}, {"id": "2055", "claim": "CNN Poll: Americans think Russia investigation is serious and should continue", "rating": "TRUE", "image_url": "['https://cdn.cnn.com/cnnnext/dam/assets/170613101920-trump-mueller-split-2-full-169.jpg']", "permalink": "", "publish_date": "20018-06-22T00:00:00+00:55", "keyword": "Americans", "twitter_url": "https://twitter.com/CNNPolitics/status/1010107903687168001", "null": ["", "", "", ""]}, {"id": "2056", "claim": "Melania Trump makes surprise visit to border facility", "rating": "TRUE", "image_url": "['https://cdn.cnn.com/cnnnext/dam/assets/180614220236-melania-trump-brower-super-169.jpg ']", "permalink": "", "publish_date": "20018-06-21T00:00:00+00:56", "keyword": "Melania visit border facility", "twitter_url": "https://twitter.com/cnnbrk/status/1009833745229209600", "null": ["", "", "", ""]}, {"id": "2057", "claim": "Koko, the gorilla who mastered sign language, has died", "rating": "TRUE", "image_url": "['https://cdn.cnn.com/cnnnext/dam/assets/180621115715-01-koko-the-gorilla-super-tease.jpg ']", "permalink": "", "publish_date": "20018-06-21T00:00:00+00:57", "keyword": "Koko gorilla language died", "twitter_url": "https://twitter.com/cnnbrk", "null": ["", "", "", ""]}, {"id": "2058", "claim": "President Trump is speaking at a rally in Duluth, Minnesota, hours after signing an order to end family separations at the border. ", "rating": "TRUE", "image_url": "['https://zenith.news/wp-content/uploads/2018/06/5ea588a5476b35fa16dd9b1014dd3973.jpg']", "permalink": "", "publish_date": "20018-06-20T00:00:00+00:58", "keyword": "Trump speakingrally Duluth", "twitter_url": "https://twitter.com/cnnbrk/status/1009583761749667841", "null": ["", "", "", ""]}, {"id": "2059", "claim": "In a rare interview, Pope Francis says family separations at the US border are \"immoral.\"", "rating": "TRUE", "image_url": "['https://cdn.cnn.com/cnn/dam/assets/160728094606-pope-francis-wall-4-tease.jpg ']", "permalink": "", "publish_date": "20018-06-20T00:00:00+00:59", "keyword": "Pope Francis separations immoral", "twitter_url": "https://twitter.com/cnnbrk/status/1009401191162437635", "null": ["", "", "", ""]}, {"id": "2060", "claim": "US announces it is withdrawing from the UN Human Rights Council", "rating": "TRUE", "image_url": "['https://cdn.cnn.com/cnnnext/dam/assets/180515170420-02-united-nations-security-council-0515-super-tease.jpg ']", "permalink": "", "publish_date": "20018-06-19T00:00:00+00:60", "keyword": "US withdrawing UN Human", "twitter_url": "https://twitter.com/cnnbrk/status/1009190726318678016", "null": ["", "", "", ""]}, {"id": "2061", "claim": "A 23-year-old man is accused of making fraudulent returns at more than 1,000 Walmart stores", "rating": "TRUE", "image_url": "['https://cdn.cnn.com/cnnnext/dam/assets/180617210550-01-man-walmart-fraud.jpg']", "permalink": "", "publish_date": "20018-06-17T00:00:00+00:61", "keyword": "23-year-old accused fraudulent Walmart", "twitter_url": "https://twitter.com/cnnbrk/status/1008529831640948737", "null": ["", "", "", ""]}, {"id": "2062", "claim": "2,000 children separated from parents at border", "rating": "TRUE", "image_url": "['https://cdn.cnn.com/cnnnext/dam/assets/180429143730-05-migrant-caravan-0429-super-tease.jpg ']", "permalink": "", "publish_date": "200children separated parent border18-06-15T00:00:00+00:62", "keyword": "", "twitter_url": "https://twitter.com/cnnbrk/status/1007709521073049601", "null": ["", "", "", ""]}, {"id": "2063", "claim": "A student showed up to his California high school dressed as a Ku Klux Klansman as part of an assignment", "rating": "TRUE", "image_url": "['https://cdn.cnn.com/cnnnext/dam/assets/180615100502-student-costume-full-169.jpg ']", "permalink": "", "publish_date": "20018-06-15T00:00:00+00:63", "keyword": "student California Klux Klansman", "twitter_url": "https://twitter.com/cnnbrk/status/1007683950456827904", "null": ["", "", "", ""]}, {"id": "2064", "claim": "The New York Attorney General is suing the Donald J. Trump Foundation and its directors", "rating": "TRUE", "image_url": "['https://cdn.cnn.com/cnnnext/dam/assets/180614105405-01-donald-trump-eric-ivanka-2014-super-tease.jpg ']", "permalink": "", "publish_date": "20018-06-14T00:00:00+00:64", "keyword": "Attorney suing Trump Foundation", "twitter_url": "https://twitter.com/cnnbrk/status/1007280254447181825", "null": ["", "", "", ""]}, {"id": "2065", "claim": "The LA District Attorney's office is reviewing a sex crime case against Sylvester Stallone", "rating": "TRUE", "image_url": "['https://ottawavalleynews.com/wp-content/uploads/2018/06/9ed7b0a3ca0197bdb1985f0a24b9b838-520x245.jpeg']", "permalink": "", "publish_date": "20018-06-13T00:00:00+00:65", "keyword": "Attorney reviewing sex Stallone", "twitter_url": "https://twitter.com/cnnbrk/status/1007103736362225664", "null": ["", "", "", ""]}, {"id": "2066", "claim": "US, Mexico and Canada chosen to host the 2026 FIFA World Cup", "rating": "TRUE", "image_url": "['https://fm.cnbc.com/applications/cnbc.com/resources/img/editorial/2018/07/06/105314430-1530876227474gettyimages-451576206.jpeg?v=1530876302']", "permalink": "", "publish_date": "20018-06-13T00:00:00+00:66", "keyword": "Mexico Canada host FIFA", "twitter_url": "https://twitter.com/CNN/status/1006854016771481600", "null": ["", "", "", ""]}, {"id": "2067", "claim": "Spain offers to take in migrant ship after Italy's populists turn it away ", "rating": "TRUE", "image_url": "['https://ichef.bbci.co.uk/news/624/cpsprodpb/2BF8/production/_101965211_cd33980f-d82f-4aaa-a5f9-e22bda10069c.jpg']", "permalink": "", "publish_date": "20018-06-10T00:00:00+00:67", "keyword": "Spain migrant Italy's populists", "twitter_url": "https://twitter.com/cnnbrk/status/1006046750895992832", "null": ["", "", "", ""]}, {"id": "2068", "claim": "Teenager from Iowa killed after ICE returns him to Mexico", "rating": "TRUE", "image_url": "['https://cdn.cnn.com/cnnnext/dam/assets/180608194647-02-manuel-antonio-cano-pacheco-super-tease.jpg']", "permalink": "", "publish_date": "20018-06-08T00:00:00+00:68", "keyword": "Teenager lowa killed ICE", "twitter_url": "https://twitter.com/cnnbrk/status/1005274200741990402", "null": ["", "", "", ""]}, {"id": "2069", "claim": "The Smithsonian once called Anthony Bourdain \"the original rock star\" of the culinary world. ", "rating": "TRUE", "image_url": "['https://twitter.com/cnnbrk/status/1005274200741990402']", "permalink": "", "publish_date": "20018-06-08T00:00:00+00:69", "keyword": "Smithsonian Anthony Bourdain culinary", "twitter_url": "https://twitter.com/cnnbrk/status/1005058294472499200", "null": ["", "", "", ""]}, {"id": "2070", "claim": "Alice Marie Johnson has been released from prison. President Trump commuted her sentence today after meeting with Kim Kardashian West last week", "rating": "TRUE", "image_url": "['https://cdn.cnn.com/cnnnext/dam/assets/180606170652-trump-kardashian-johnson-inset-super-169.jpg ']", "permalink": "", "publish_date": "20018-06-06T00:00:00+00:70", "keyword": "Alice Marie released Trump", "twitter_url": "https://twitter.com/cnnbrk/status/1004493780706357248", "null": ["", "", "", ""]}, {"id": "2071", "claim": "ICE arrested 114 undocumented immigrants working at an Ohio gardening business in one of its largest workplace raids in recent years", "rating": "TRUE", "image_url": "['https://localtvwtvr.files.wordpress.com/2018/06/180606143308-corsos-garden-ice-arrests-exlarge-169.jpg?quality=85&strip=all']", "permalink": "", "publish_date": "20018-06-06T00:00:00+00:71", "keyword": "ICE arrested immigrants Ohio", "twitter_url": "https://twitter.com/cnnbrk/status/1004469511087689730", "null": ["", "", "", ""]}, {"id": "2072", "claim": "Trump commutes sentence of Alice Marie Johnson", "rating": "TRUE", "image_url": "['https://cdn.cnn.com/cnnnext/dam/assets/161228155732-alice-johnson-headshot-super-tease.jpg ']", "permalink": "", "publish_date": "20018-06-06T00:00:00+00:72", "keyword": "Trump commutes sentence Alice ", "twitter_url": "https://twitter.com/cnnbrk/status/1004403699500937216", "null": ["", "", "", ""]}, {"id": "2073", "claim": "Miss America is scrapping the swimsuit portion from its pageant", "rating": "TRUE", "image_url": "['https://cdn1.bbend.net/media/com_news/galleries/2018/06/05/43801/photos/thumb/missamerica.jpg']", "permalink": "", "publish_date": "20018-06-05T00:00:00+00:73", "keyword": "Miss America scarpping pageant", "twitter_url": "https://twitter.com/cnnbrk/status/1003988948820070400", "null": ["", "", "", ""]}, {"id": "2074", "claim": "Trump cancels Philadelphia Eagles visit to the White House", "rating": "TRUE", "image_url": "['https://s2-ssl.dmcdn.net/qkh2k/x240-bQu.jpg']", "permalink": "", "publish_date": "20018-06-04T00:00:00+00:74", "keyword": "Trump cancel Philadelphia Eagles", "twitter_url": "https://twitter.com/cnnbrk/status/1003786647329230848", "null": ["", "", "", ""]}, {"id": "2075", "claim": "The Supreme Court hands a narrow win to the Colorado baker who refused to design a cake for a same-sex wedding", "rating": "TRUE", "image_url": "['https://cdn.cnn.com/cnnnext/dam/assets/180604102723-01-co-baker-jack-phillips-file-super-tease.jpg ']", "permalink": "", "publish_date": "20018-06-04T00:00:00+00:75", "keyword": "Supreme win Colorado baker", "twitter_url": "https://twitter.com/cnnbrk/status/1003645311250780161", "null": ["", "", "", ""]}, {"id": "2076", "claim": "Dog dies during Delta Air Lines layover in Michigan ", "rating": "TRUE", "image_url": "['https://cdn.cnn.com/cnnnext/dam/assets/170407203807-delta-airlines-plane-july-2016-medium-plus-169.jpg']", "permalink": "", "publish_date": "20018-06-02T00:00:00+00:76", "keyword": "Dog dies Delta layover", "twitter_url": "https://twitter.com/cnnbrk/status/1003087229378547713", "null": ["", "", "", ""]}, {"id": "2077", "claim": "ABC is considering a version of \"Roseanne\" ¡ª without Roseanne Barr", "rating": "TRUE", "image_url": "['https://i.kinja-img.com/gawker-media/image/upload/s--YKPKhvrj--/c_fill,fl_progressive,g_center,h_900,q_80,w_1600/dtql5intploxh2gao7ay.jpg']", "permalink": "", "publish_date": "20018-06-01T00:00:00+00:77", "keyword": "ABC considering Roseanne Barr", "twitter_url": "https://twitter.com/CNNMoney/status/1002660258693738496", "null": ["", "", "", ""]}, {"id": "2078", "claim": "Comedian Samantha Bee apologizes for her vulgar remark about Ivanka Trump", "rating": "TRUE", "image_url": "['https://i2.cdn.turner.com/money/dam/assets/180109155609-samantha-bee-full-frontal-1100x619.jpg']", "permalink": "", "publish_date": "20018-05-31T00:00:00+00:78", "keyword": "Samantha Bee apologizes Ivanka", "twitter_url": "https://twitter.com/cnnbrk/status/1002261946715041792", "null": ["", "", "", ""]}, {"id": "2079", "claim": "Kim Kardashian meets with Trump to discuss prison reform", "rating": "TRUE", "image_url": "['https://cbsdetroit.files.wordpress.com/2018/05/s094448605.jpg']", "permalink": "", "publish_date": "20018-05-30T00:00:00+00:79", "keyword": "Kardashian Trump prison reform", "twitter_url": "https://twitter.com/cnnbrk/status/1001818593720504326", "null": ["", "", "", ""]}, {"id": "2080", "claim": "US lost track of 1,500 immigrant children, but says it's not 'legally responsible'", "rating": "TRUE", "image_url": "['https://cdn.cnn.com/cnnnext/dam/assets/180526091533-central-america-migrant-caravan-0415-restricted-super-tease.jpg']", "permalink": "", "publish_date": "20018-05-26T00:00:00+00:80", "keyword": "US lost immigrant children", "twitter_url": "https://twitter.com/CNNPolitics/status/1000452023500853250", "null": ["", "", "", ""]}, {"id": "2081", "claim": "Ireland votes resoundingly to repeal abortion ban", "rating": "TRUE", "image_url": "['https://pbs.twimg.com/media/DeI8SdsWAAEG_FI.jpg ']", "permalink": "", "publish_date": "20018-05-26T00:00:00+00:81", "keyword": "Ireland votes repeal abortion", "twitter_url": "https://twitter.com/cnnbrk/status/1000428385770852354", "null": ["", "", "", ""]}, {"id": "2082", "claim": "Visa suspends Morgan Freeman campaign after accusations of inappropriate behavior ", "rating": "TRUE", "image_url": "['https://www.estrelando.com.br/uploads/2018/05/28/1-1527538899.jpg']", "permalink": "", "publish_date": "20018-05-25T00:00:00+00:82", "keyword": "Visa suspending Mogan inappropriate", "twitter_url": "https://twitter.com/cnnbrk/status/1000110684821127169", "null": ["", "", "", ""]}, {"id": "2083", "claim": "An armed citizen killed a shooter at an Oklahoma City restaurant", "rating": "TRUE", "image_url": "['http://pbs.twimg.com/media/DeAVG2EUwAA9EwC.jpg']", "permalink": "", "publish_date": "20018-05-24T00:00:00+00:83", "keyword": "citizen killed shooter Oklahoma", "twitter_url": "https://twitter.com/cnnbrk/status/999823404176945153", "null": ["", "", "", ""]}, {"id": "2084", "claim": "Brexit Secretary David Davis resigns from the UK government", "rating": "TRUE", "image_url": "['https://ichef.bbci.co.uk/images/ic/1024x576/p06d8xrf.jpg']", "permalink": "", "publish_date": "20018-06-08T00:00:00+00:84", "keyword": "Brexit David Davis resigns", "twitter_url": "https://twitter.com/BBCBreaking/status/1016092776952365056", "null": ["", "", "", ""]}, {"id": "2085", "claim": "Four Thai boys rescued but rest must wait", "rating": "TRUE", "image_url": "['https://image-us.eva.vn/upload/3-2018/images/2018-07-08/1531063575-197-thumbnail_schema_article.jpg']", "permalink": "", "publish_date": "20018-07-08T00:00:00+00:85", "keyword": "Thai rescued rest wait", "twitter_url": "https://twitter.com/BBCBreaking/status/1015928781905723393", "null": ["", "", "", ""]}, {"id": "2086", "claim": "England have reached a WorldCup semi-final for the first time since 1990! ", "rating": "TRUE", "image_url": "['https://pbs.twimg.com/media/Dhg6sHSWkAEQios.jpg:large']", "permalink": "", "publish_date": "20018-07-07T00:00:00+00:86", "keyword": "England reached worldcup semi-final ", "twitter_url": "https://twitter.com/BBCSport/status/1015624400257810432", "null": ["", "", "", ""]}, {"id": "2087", "claim": "Pakistan's ex-PM Nawaz Sharif given 10 year prison term over corruption allegations related to London luxury flats", "rating": "TRUE", "image_url": "['https://i.pinimg.com/736x/33/9e/59/339e59106f9961347d5b934dfe2da167.jpg']", "permalink": "", "publish_date": "20018-07-06T00:00:00+00:88", "keyword": "Pakistan's Nawaz prison corruption", "twitter_url": "https://twitter.com/BBCBreaking/status/1015196751442141184", "null": ["", "", "", ""]}, {"id": "2088", "claim": "\nEngland have won on penalties! Eric Dier!\n", "rating": "TRUE", "image_url": "['http://www.kan98.com/uploadfile/2018/0704/20180704054334163.jpg']", "permalink": "", "publish_date": "20018-07-03T00:00:00+00:89", "keyword": "England won penalties worldcup", "twitter_url": "https://twitter.com/BBCSport/status/1014250650111234048", "null": ["", "", "", ""]}, {"id": "2089", "claim": "Several people dead in shooting at newspaper building in US city of Annapolis in Maryland", "rating": "TRUE", "image_url": "['https://2.bp.blogspot.com/-2gFH2WNWZK0/WzXXDBScvjI/AAAAAAAAUyY/-_0wEnn0Uf4DPTkmro7-PxL_pBbip6YEACLcBGAs/s1600/_102254478_b1464c78-bc0a-4a7c-82cc-34dfb57be67b.jpg']", "permalink": "", "publish_date": "20018-06-28T00:00:00+00:89", "keyword": "dead shooting newspaper Annapolis", "twitter_url": "https://twitter.com/BBCBreaking/status/1012436376976084993", "null": ["", "", "", ""]}, {"id": "2090", "claim": "A Supreme Court justice is to retire", "rating": "TRUE", "image_url": "['https://thechristians.com/wp-content/uploads/2018/07/20180705-Opinion-Blake-640x450.png']", "permalink": "", "publish_date": "20018-06-T00:00:00+00:90", "keyword": "Supreme justice retire reshape", "twitter_url": "https://twitter.com/BBCBreaking/status/1012037403635339276", "null": ["", "", "", ""]}, {"id": "2091", "claim": "Joe Jackson, the father and manager of Michael Jackson and the Jackson Five, has died aged 89", "rating": "TRUE", "image_url": "['http://images.gmanews.tv/webpics/2018/06/Joe_Jackson_with_the_late_Michael_Jackson_2018_06_28_02_11_34.JPG']", "permalink": "", "publish_date": "20018-06-27T00:00:00+00:91", "keyword": "Joe Jackson died 89", "twitter_url": "https://twitter.com/BBCBreaking/status/1012015557577773058", "null": ["", "", "", ""]}, {"id": "2092", "claim": "Civil partnership win for mixed-sex couple", "rating": "TRUE", "image_url": "['https://ebookvault.biz/wp-content/uploads/2018/06/a305e0749406e281c8f220d41d2cfb31-780x350.jpeg']", "permalink": "", "publish_date": "20018-06-27T00:00:00+00:92", "keyword": "Civil partnership win mixed-sex", "twitter_url": "https://twitter.com/BBCBreaking/status/1011894769692405760", "null": ["", "", "", ""]}, {"id": "2093", "claim": "Taliban bomb-maker guilty of Westminster plot. ", "rating": "TRUE", "image_url": "['http://www.rajofm.com/wp-content/uploads/2018/06/2018627636656606768955954Ali5-534x351.jpg']", "permalink": "", "publish_date": "20018-06-26T00:00:00+00:93", "keyword": "Taliban bomb-maker guilty Westminster", "twitter_url": "https://twitter.com/BBCBreaking/status/1011600137125232640", "null": ["", "", "", ""]}, {"id": "2094", "claim": "MPs back Heathrow airport expansion", "rating": "TRUE", "image_url": "['https://www.irishtimes.com/polopoly_fs/1.3524312.1528483402!/image/image.jpg_gen/derivatives/landscape_685/image.jpg']", "permalink": "", "publish_date": "20018-06-25T00:00:00+00:94", "keyword": "MPs Heathrow airport expansion", "twitter_url": "https://twitter.com/BBCBreaking/status/1011358485349568512", "null": ["", "", "", ""]}, {"id": "2095", "claim": "Saudi women celebrate end of driving ban", "rating": "TRUE", "image_url": "['http://www.bizshala.com/public/images/cache/news/2018-06-24/290x188-1529817910bbc.jpg']", "permalink": "", "publish_date": "20018-06-23T00:00:00+00:95", "keyword": "Saudi women end driving", "twitter_url": "https://twitter.com/BBCBreaking/status/1010636961009291264", "null": ["", "", "", ""]}, {"id": "2096", "claim": "Canada will legalise marijuana for recreational use after a landmark law passes the Senate", "rating": "TRUE", "image_url": "['https://www.b92.net/news/pics/2018/06/20/d464f1338fedd1accda8fae0bd482355_640x360.jpg']", "permalink": "", "publish_date": "20018-06-19T00:00:00+00:96", "keyword": "Canada legalises recreational cannabis", "twitter_url": "https://twitter.com/BBCBreaking/status/1009219346592354304", "null": ["", "", "", ""]}, {"id": "2097", "claim": "US quits 'biased' UN human rights council", "rating": "TRUE", "image_url": "['https://niuerdata.g.com.cn/data/shareimg_oss/new_thumb/2018/06/21/thumb_b41193f26e89b307c835aaab9a4f3757.JPEG']", "permalink": "", "publish_date": "20018-06-19T00:00:00+00:97", "keyword": "US quits UN human ", "twitter_url": "https://twitter.com/BBCBreaking/status/1009182003059744770", "null": ["", "", "", ""]}, {"id": "2098", "claim": "Rapper XXXTentacion shot dead in Florida", "rating": "TRUE", "image_url": "['https://i0.wp.com/www.betatalk.com.ng/wp-content/uploads/2018/06/rapper-xxxtentacion-shot-dead-in-florida4.jpg?fit=640%2C360']", "permalink": "", "publish_date": "20018-06-18T00:00:00+00:98", "keyword": "XXXTentacion shot dead Florida", "twitter_url": "https://twitter.com/BBCBreaking/status/1008841128454643712", "null": ["", "", "", ""]}, {"id": "2099", "claim": "Epileptic boy gets cannabis oil back.", "rating": "TRUE", "image_url": "['https://s3-eu-west-2.amazonaws.com/metro-news-s3-prod/wp-content/uploads/2018/06/Header_1778220_16.9.jpg']", "permalink": "", "publish_date": "20018-06-16T00:00:00+00:99", "keyword": "Epileptic boy cannabis back", "twitter_url": "https://twitter.com/BBCBreaking/status/1007955627057012737", "null": ["", "", "", ""]}, {"id": "2100", "claim": "Major fire devastates Glasgow School of Art", "rating": "TRUE", "image_url": "['https://ichef.bbci.co.uk/images/ic/1024x576/p06b8gvh.jpg ']", "permalink": "", "publish_date": "20018-06-15T00:00:00+00:100", "keyword": "fire devastates Glasgow school", "twitter_url": "https://twitter.com/BBCBreaking/status/1007770184319414273", "null": ["", "", "", ""]}, {"id": "2101", "claim": "Spain says it will accept rescue ship with hundreds of migrants aboard", "rating": "TRUE", "image_url": "['https://ichef.bbci.co.uk/images/ic/720x405/p069sshj.jpg ']", "permalink": "", "publish_date": "20018-06-11T00:00:00+00:101", "keyword": "Spain accept rescue migrants", "twitter_url": "https://twitter.com/BBCBreaking/status/1006154955059810304", "null": ["", "", "", ""]}, {"id": "2102", "claim": "G7 summit ends in disarray over tariffs. ", "rating": "TRUE", "image_url": "['https://www.ctvnews.ca/polopoly_fs/1.3967883.1528688058!/httpImage/image.jpg_gen/derivatives/landscape_620/image.jpg']", "permalink": "", "publish_date": "20018-06-09T00:00:00+00:102", "keyword": "G7 summit disarray tariffs", "twitter_url": "https://twitter.com/BBCBreaking/status/1005598516025155584", "null": ["", "", "", ""]}, {"id": "2103", "claim": "Actress Emma Thompson becomes a dame, with Liverpool legend Kenny Dalglish knighted", "rating": "TRUE", "image_url": "['https://pbs.twimg.com/media/DfMw7NbVAAA7Mjl.jpg']", "permalink": "", "publish_date": "20018-06-08T00:00:00+00:103", "keyword": "Emma Thompson dame Liverpool", "twitter_url": "https://twitter.com/BBCBreaking", "null": ["", "", "", ""]}, {"id": "2104", "claim": "Man charged with manslaughter of 100-year-old woman", "rating": "TRUE", "image_url": "['https://pbs.twimg.com/media/DfA0eAQW4AAj6Y6.jpg']", "permalink": "", "publish_date": "20018-06-08T00:00:00+00:104", "keyword": "man charged manslaughter 100-year-old", "twitter_url": "https://twitter.com/BBCBreaking/status/1005131726815924224", "null": ["", "", "", ""]}, {"id": "2105", "claim": "US celebrity chef and writer Anthony Bourdain found dead in French hotel room at age of 61", "rating": "TRUE", "image_url": "['https://www.thinkactive.in/wp-content/uploads/2018/06/1755/p069ks8c-390x205.jpg']", "permalink": "", "publish_date": "20018-06-08T00:00:00+00:105", "keyword": "Anthony Bourdain dead hotel", "twitter_url": "https://twitter.com/BBCBreaking", "null": ["", "", "", ""]}, {"id": "2106", "claim": "House of Fraser to close 31 stores", "rating": "TRUE", "image_url": "['http://startupnewsdigest.com/wp-content/uploads/2018/06/p069fvfl-390x205.jpg']", "permalink": "", "publish_date": "20018-06-06T00:00:00+00:106", "keyword": "House Fraser close stores", "twitter_url": "https://twitter.com/BBCBreaking/status/1004618727604793344", "null": ["", "", "", ""]}, {"id": "2107", "claim": "Trump grants Kardashian's clemency plea", "rating": "TRUE", "image_url": "['https://images.perthnow.com.au/publication/475E730846583B34E71B86D1D1C15FB0/1528440637842_1654d71c5ef732a17124ca9151c2c967.jpeg?imwidth=1024']", "permalink": "", "publish_date": "20018-06-06T00:00:00+00:107", "keyword": "Trump grants Kardashian's plea", "twitter_url": "https://twitter.com/BBCBreaking/status/1004403904296243203", "null": ["", "", "", ""]}, {"id": "2108", "claim": "Fashion designer Kate Spade found dead", "rating": "TRUE", "image_url": "['https://ichef.bbci.co.uk/news/208/cpsprodpb/16B15/production/_101894929_p0697r1d.jpg']", "permalink": "", "publish_date": "20018-06-05T00:00:00+00:108", "keyword": "Kate Spade found dead", "twitter_url": "https://twitter.com/BBCBreaking/status/1004033430382784515", "null": ["", "", "", ""]}, {"id": "2109", "claim": "US Supreme Court rules in favour of Christian baker who refused Colorado couple's request", "rating": "TRUE", "image_url": "['https://ichef.bbci.co.uk/news/1024/branded_news/14B31/production/_99058748_ef59f458-b3c1-427c-ba07-0c968291c033.jpg']", "permalink": "", "publish_date": "20018-06-04T00:00:00+00:109", "keyword": "court backs baker's gay", "twitter_url": "https://twitter.com/BBCBreaking/status/1003646554761322496", "null": ["", "", "", ""]}, {"id": "2110", "claim": "Visa says some card payments are currently failing across the UK and elsewhere in Europe", "rating": "TRUE", "image_url": "['https://media.licdn.com/media-proxy/ext?w=800&h=800&hash=OIrZpFx%2FIYixbNTbPCawOAj2A30%3D&ora=1%2CaFBCTXdkRmpGL2lvQUFBPQ%2CxAVta5g-0R6nlh8Tw1It6a2FowGz60oISIfYC2G8G2f1spyfNT-tdoDSeLKjoEtOdSkGlhJkcrG-GGGiSp6pKfyKII12yMyjLOWgQSIUbzQ_lXNhuPIJbAph57KHQLjUJiFc07EJKH2eMp_LRGYHDi4F8PyuAdXUP2wk_3S8fJ2zOtRkaKNjpYYXk2wDrcbnOcwm7qVgnHk74Qrs5YbrOhIhyJqxMWmGKBsCA1LPB-9UjYaO02GkqnvzvFzI99uIUYOmIPQcxn-8_tPaUl-hv1ZkjTgN0Sg2vt9zBSKBhoAz4mqaFOcKfkq8ssO9H3T8qZlF-RMKkeWHCweZdQ']", "permalink": "", "publish_date": "20018-06-01T00:00:00+00:110", "keyword": "Visa payments failing UK ", "twitter_url": "https://twitter.com/BBCBreaking/status/1002578214810681344", "null": ["", "", "", ""]}, {"id": "2111", "claim": "Five big cats which escaped from a zoo in western Germany have been recaptured", "rating": "TRUE", "image_url": "['https://img.wp.de/img/incoming/crop214449919/8621862802-w1024-cv3_2-q85/Loewe-Malor-liegt-in-seinem-Gehege-im-Eifel-Zoo-in-Luenebach-waehrend-im-Vordergrund-seine-Mutter-Lira-vorbeilaeuft.jpg']", "permalink": "", "publish_date": "20018-06-01T00:00:00+00:111", "keyword": "Escaped cats Germany recaptured", "twitter_url": "https://twitter.com/BBCBreaking/status/1002524483880710144", "null": ["", "", "", ""]}, {"id": "2112", "claim": "The US to put tariffs on steel and aluminium made by key allies", "rating": "TRUE", "image_url": "['https://www.matichon.co.th/wp-content/uploads/2018/06/IMG_7009.jpg']", "permalink": "", "publish_date": "20018-05-31T00:00:00+00:112", "keyword": "US imposes metal tariffs", "twitter_url": "https://twitter.com/BBCBreaking/status/1002184288358551556", "null": ["", "", "", ""]}, {"id": "2113", "claim": "\"Assassination\" of journalist Arkady Babchenko was \"staged to expose Russian agents\"", "rating": "TRUE", "image_url": "['https://i0.wp.com/global-news-network.org/wp-content/uploads/2018/05/8355/p068p4qk.jpg?resize=324%2C160']", "permalink": "", "publish_date": "20018-05-T00:00:00+00:113", "keyword": "Arkady Babchenko expose Russian", "twitter_url": "https://twitter.com/BBCBreaking/status/1001838015747182593", "null": ["", "", "", ""]}, {"id": "2114", "claim": "Hurricane Maria killed 4,600 people in Puerto Rico", "rating": "TRUE", "image_url": "['https://fm.cnbc.com/applications/cnbc.com/resources/img/editorial/2017/09/22/104725738-GettyImages-850860386.jpg?v=1513614084']", "permalink": "", "publish_date": "20018-05-29T00:00:00+00:114", "keyword": "Hurrican Maria killed Puerto Rico", "twitter_url": "https://twitter.com/BBCBreaking/status/1001472575568920576", "null": ["", "", "", ""]}, {"id": "2115", "claim": "It's heartbreak for Liverpool as Real Madrid win their 13th Champions League title. ", "rating": "TRUE", "image_url": "['https://scontent-frx5-1.cdninstagram.com/vp/17b2160ca338c2fc788e1ea5037386fd/5BC30312/t51.2885-15/s640x640/sh0.08/e35/32225321_1573841969408728_7209052509837459456_n.jpg']", "permalink": "", "publish_date": "20018-05-26T00:00:00+00:116", "keyword": "Liverpool Madrid win Champions", "twitter_url": "https://twitter.com/BBCSport/status/1000476246101372928", "null": ["", "", "", ""]}, {"id": "2116", "claim": "Republic of Ireland votes resoundingly to overturn abortion ban with voters backing reform of constitution ", "rating": "TRUE", "image_url": "['https://laopinionla.files.wordpress.com/2018/05/101763878_gettyimages-962652888.jpg?quality=60&strip=all&w=300']", "permalink": "", "publish_date": "20018-05-26T00:00:00+00:117", "keyword": "Ireland vote overturn abortion", "twitter_url": "https://twitter.com/BBCBreaking/status/1000425837122990080", "null": ["", "", "", ""]}, {"id": "2117", "claim": "Exit polls suggest the Republic of Ireland has voted by a landslide to liberalise its strict abortion laws", "rating": "TRUE", "image_url": "['https://my-day.live/wp-content/uploads/2018/05/92.jpg']", "permalink": "", "publish_date": "20018-05-25T00:00:00+00:117", "keyword": "Ireland vote liberalise abortion", "twitter_url": "https://twitter.com/BBCBreaking/status/1000141490155327489", "null": ["", "", "", ""]}, {"id": "2118", "claim": "Evil acid attacker gets life sentence", "rating": "TRUE", "image_url": "['http://www.gazette-news.co.uk/resources/images/7802930/']", "permalink": "", "publish_date": "20018-05-23T00:00:00+00:118", "keyword": "Berlinah Wallace life sentence", "twitter_url": "https://twitter.com/BBCBreaking/status/999223334188527616", "null": ["", "", "", ""]}, {"id": "2119", "claim": "Duke and Duchess of Sussex release official photographs from their wedding day", "rating": "TRUE", "image_url": "['https://www.svtstatic.se/image-cms/svtse/1526926118/svts/article18092935.svt/BINARY/original/1526913062779-g491kq268-2-2-jpg']", "permalink": "", "publish_date": "20018-05-21T00:00:00+00:119", "keyword": "Duke release official photographs", "twitter_url": "https://twitter.com/BBCBreaking/status/998566347792666624", "null": ["", "", "", ""]}, {"id": "2120", "claim": "At least eight people are dead after a shooting at Santa Fe High School in Texas", "rating": "TRUE", "image_url": "['https://ichef.bbci.co.uk/images/ic/1024x576/p067lmm5.jpg']", "permalink": "", "publish_date": "20018-05-18T00:00:00+00:120", "keyword": "dead shooting Santa Fe", "twitter_url": "https://twitter.com/BBCBreaking/status/997496521540210688", "null": ["", "", "", ""]}, {"id": "2121", "claim": "Meghan's father may not attend wedding.", "rating": "TRUE", "image_url": "['https://ichef.bbci.co.uk/news/912/cpsprodpb/5F92/production/_101566442_hi043248122.jpg']", "permalink": "", "publish_date": "20018-05-14T00:00:00+00:121", "keyword": "Meghan's father not attend ", "twitter_url": "https://twitter.com/BBCBreaking/status/996124276829941761", "null": ["", "", "", ""]}, {"id": "2122", "claim": "Numbers of casualties continue to rise in deadliest day of violence since the 2014 Gaza war", "rating": "TRUE", "image_url": "['https://pbs.twimg.com/media/DdK8DLNXUAEjj4e.jpg']", "permalink": "", "publish_date": "20018-05-14T00:00:00+00:122", "keyword": "casualties rise deadliest Gaza", "twitter_url": "https://twitter.com/BBCBreaking/status/996067481365164032", "null": ["", "", "", ""]}, {"id": "2123", "claim": "Gaza health officials say at least 37 Palestinians killed", "rating": "TRUE", "image_url": "['https://img.tsn.ua/cached/1526389867/tsn-8c5f6b23d1211bb14030cc3abd4583f7/thumbs/1200x630/fd/d2/1d65ed98d59aa57b60b470905761d2fd.jpeg']", "permalink": "", "publish_date": "20018-05-14T00:00:00+00:123", "keyword": "Gaza 37 Palestinians killed", "twitter_url": "https://twitter.com/BBCBreaking/status/996009687916085253", "null": ["", "", "", ""]}, {"id": "2124", "claim": "Former Labour cabinet minister Dame Tessa Jowell has died aged 70", "rating": "TRUE", "image_url": "['https://ichef.bbci.co.uk/news/208/cpsprodpb/A12E/production/_99726214_p05vv2yw.jpg']", "permalink": "", "publish_date": "20018-05-12T00:00:00+00:124", "keyword": "Dame Tessa Jowell died", "twitter_url": "https://twitter.com/BBCBreaking/status/995552895440510978", "null": ["", "", "", ""]}, {"id": "2125", "claim": "Israel's NettaBarzilai wins this year's eurovision song contest ", "rating": "TRUE", "image_url": "['https://static.cnews.fr/sites/default/files/000_14u8l0.jpg']", "permalink": "", "publish_date": "20018-05-12T00:00:00+00:125", "keyword": "Israel's NettaBarzilai wins eurovision ", "twitter_url": "https://twitter.com/BBCBreaking/status/995440051688497153", "null": ["", "", "", ""]}, {"id": "2126", "claim": "Promising teen, Thyhiem Ainsworth Barton, dies in London shooting", "rating": "TRUE", "image_url": "['https://pbs.twimg.com/media/DckNJNcWkAA3xU2.jpg']", "permalink": "", "publish_date": "20018-05-05T00:00:00+00:126", "keyword": "Barton died gunshot London", "twitter_url": "https://twitter.com/BBCBreaking/status/993013449537015808", "null": ["", "", "", ""]}, {"id": "2127", "claim": "Former Man Utd manager Sir Alex Ferguson has had emergency surgery for brain haemorrhage", "rating": "TRUE", "image_url": "['https://i1.wp.com/234radio.com/wp-content/uploads/2018/05/101192513_ferguson_trophy_1getty.jpg?fit=1024%2C576&resize=350%2C200']", "permalink": "", "publish_date": "20018-05-05T00:00:00+00:127", "keyword": "Alex Ferguson emergency surgery", "twitter_url": "https://twitter.com/BBCBreaking/status/992842607217782791", "null": ["", "", "", ""]}, {"id": "2128", "claim": "UK MPs vote against opposition motion to reveal Home Office documents on Windrush migrants", "rating": "TRUE", "image_url": "['https://images.theconversation.com/files/224275/original/file-20180621-137738-duhqjg.jpg?ixlib=rb-1.1.0&q=45&auto=format&w=754&fit=clip']", "permalink": "", "publish_date": "20018-05-2T00:00:00+00:128", "keyword": "MPs vote against Windrush", "twitter_url": "https://twitter.com/BBCBreaking/status/991743946857615360", "null": ["", "", "", ""]}, {"id": "2129", "claim": "Home Secretary Amber Rudd resigns", "rating": "TRUE", "image_url": "['https://i.ytimg.com/vi/RmLS1AgeYYI/hqdefault.jpg?sqp=-oaymwEWCKgBEF5IWvKriqkDCQgBFQAAiEIYAQ==&rs=AOn4CLD66jgvUhUkbV2Oop5Lib9ziF-scg']", "permalink": "", "publish_date": "20018-04-29T00:00:00+00:129", "keyword": "Amber Rudd resigns secretary", "twitter_url": "https://twitter.com/BBCBreaking/status/990698488710225921", "null": ["", "", "", ""]}, {"id": "2130", "claim": "North Korea's nuclear test site will close in May", "rating": "TRUE", "image_url": "['https://newsmanonline.com/wp-content/uploads/2018/04/101088449_b3a5508d-bbad-477b-a039-08ce2e5a726e.jpg']", "permalink": "", "publish_date": "20018-04-28T00:00:00+00:130", "keyword": "North Korea nuclear close", "twitter_url": "https://twitter.com/BBCBreaking/status/990413332325785605", "null": ["", "", "", ""]}, {"id": "2131", "claim": "Legal battle roddler Alfie Evans dies", "rating": "TRUE", "image_url": "['https://c.files.bbci.co.uk/E86D/production/_101010595_alfieevans2.jpg']", "permalink": "", "publish_date": "20018-04-27T00:00:00+00:131", "keyword": "toddler Alfie Evans dies", "twitter_url": "https://twitter.com/BBCBreaking/status/990109137882304512", "null": ["", "", "", ""]}, {"id": "2132", "claim": "Duke & Duchess of Cambridge name royalbaby Louis Arthur Charles ", "rating": "TRUE", "image_url": "['http://inews.gtimg.com/newsapp_match/0/3372952050/0']", "permalink": "", "publish_date": "20018-04-27T00:00:00+00:132", "keyword": "Duke name Louis Arthur", "twitter_url": "https://twitter.com/BBCBreaking/status/989807212167131137", "null": ["", "", "", ""]}, {"id": "2133", "claim": "Ruth Davidson, Scottish Tory leader, says she is pregnant and she and partner Jen Wilson \"excited\"", "rating": "TRUE", "image_url": "['https://www.thetimes.co.uk/imageserver/image/methode%2Ftimes%2Fprod%2Fweb%2Fbin%2F2ca0dc36-43f2-11e8-99ea-a5dd07dd144b.jpg?crop=2533%2C1425%2C0%2C0']", "permalink": "", "publish_date": "20018-04-26T00:00:00+00:133", "keyword": "Ruth Davidson Tory pregnant ", "twitter_url": "https://twitter.com/BBCBreaking/status/989526675460325376", "null": ["", "", "", ""]}, {"id": "2134", "claim": "India jails rapist guru Asaram for life", "rating": "TRUE", "image_url": "['https://khairopati.com/wp-content/uploads/2018/04/406-300x182.jpg']", "permalink": "", "publish_date": "20018-04-24T00:00:00+00:134", "keyword": "Indian Asaram jails rape", "twitter_url": "https://twitter.com/BBCBreaking/status/989012121429168129", "null": ["", "", "", ""]}, {"id": "2135", "claim": "The Duke & Duchess of Cambridge announce the birth of their second son", "rating": "TRUE", "image_url": "['https://pbs.twimg.com/media/Dbd1zmEXcAAGsTO.jpg']", "permalink": "", "publish_date": "20018-04-23T00:00:00+00:135", "keyword": "Duchess Cambridge second son", "twitter_url": "https://twitter.com/BBCBreaking/status/988388726408712193", "null": ["", "", "", ""]}, {"id": "2136", "claim": "Duchess of Cambridge in labour", "rating": "TRUE", "image_url": "['https://cdn.newsapi.com.au/image/v1/0f56289411e6008d4e27947f63fca801?width=1024']", "permalink": "", "publish_date": "20018-04-23T00:00:00+00:136", "keyword": "Duchess Cambridge in labour", "twitter_url": "https://twitter.com/BBCBreaking/status/988318635285467136", "null": ["", "", "", ""]}, {"id": "2137", "claim": "Mini-Me actor Verne Troyer dies at 49", "rating": "TRUE", "image_url": "['https://www.nation.co.ke/image/view/-/4492904/medRes/1946334/-/ypvi9dz/-/T1.jpg']", "permalink": "", "publish_date": "20018-04-21T00:00:00+00:137", "keyword": "Verne Troyer dies 49", "twitter_url": "https://twitter.com/BBCBreaking", "null": ["", "", "", ""]}, {"id": "2138", "claim": "Swedish DJ Avicii has died in Oman at the age of 28", "rating": "TRUE", "image_url": "['http://livedoor.blogimg.jp/music075/imgs/d/5/d5aa5aa4.jpg']", "permalink": "", "publish_date": "20018-04-20T00:00:00+00:138", "keyword": "Avicii died Oman 28", "twitter_url": "https://twitter.com/BBCBreaking/status/987385353144332289", "null": ["", "", "", ""]}, {"id": "2139", "claim": "Commonwealth leaders agree that Prince Charles will be the next head of the organisation", "rating": "TRUE", "image_url": "['http://m.eirinika.gr/sites/default/files/sitefiles_2018-04/4b54be8b00000578-5637633-commonwealth_leaders_are_today_set_to_decide_if_prince_charles_w-a-22_1524218137984.jpg']", "permalink": "", "publish_date": "20018-04-20T00:00:00+00:139", "keyword": "Commonwealth Charles next organisation", "twitter_url": "https://twitter.com/BBCBreaking/status/987301468121255936", "null": ["", "", "", ""]}, {"id": "2140", "claim": "TV presenter Ant McPartlin fined ?86,000 and banned from driving for 20 months, after admitting drink driving", "rating": "TRUE", "image_url": "['https://ichef.bbci.co.uk/news/1024/branded_news/850C/production/_100906043_p064gw5q.jpg']", "permalink": "", "publish_date": "20018-04-16T00:00:00+00:140", "keyword": "McPartlin banned driving drink", "twitter_url": "https://twitter.com/BBCBreaking/status/985881062990667776", "null": ["", "", "", ""]}, {"id": "2141", "claim": "Inspectors back UK in spy poisonig row", "rating": "TRUE", "image_url": "['https://www.gannett-cdn.com/-mm-/eb082c45a0f6d278cd5868985f7549d4334da985/c=0-134-4000-2394/local/-/media/2018/03/09/USATODAY/USATODAY/636561915604614560-GTY-929239864.jpg?width=3200&height=1680&fit=crop']", "permalink": "", "publish_date": "20018-04-12T00:00:00+00:141", "keyword": "Inspectors UK spy poisoning", "twitter_url": "https://twitter.com/BBCBreaking/status/984749685201166336", "null": ["", "", "", ""]}, {"id": "2142", "claim": "Two killed as van drives into German crowd", "rating": "TRUE", "image_url": "['https://www.ilpost.it/wp-content/uploads/2018/04/munster-1.jpg']", "permalink": "", "publish_date": "20018-04-07T00:00:00+00:142", "keyword": "two killed van German", "twitter_url": "https://twitter.com/BBCBreaking/status/982633971254222850", "null": ["", "", "", ""]}, {"id": "2143", "claim": "WHO demands 'chemical attack site' access", "rating": "TRUE", "image_url": "['https://www.mnnofa.com/wp-content/uploads/2018/04/syria-chemical-attack-trump-decision-on-strike-fairly-soon-480x270.jpg']", "permalink": "", "publish_date": "20018-04-T00:00:00+00:143", "keyword": "WHO demand chemical site", "twitter_url": "https://twitter.com/BBCBreaking/status/983998775302770690", "null": ["", "", "", ""]}, {"id": "2144", "claim": "Roma have knocked Barcelona out of the Champions League on away goals! ", "rating": "TRUE", "image_url": "['https://i.eurosport.com/2018/04/10/2311085-48120477-1600-900.jpg']", "permalink": "", "publish_date": "20018-04-10T00:00:00+00:144", "keyword": "Roma knock Barcelona League", "twitter_url": "https://twitter.com/BBCSport/status/983805634595475456", "null": ["", "", "", ""]}, {"id": "2145", "claim": "Trump condemns Syria for 'chemical attack'", "rating": "TRUE", "image_url": "['https://2.bp.blogspot.com/-ceQz2_VzzLk/Ws7tKB0L9yI/AAAAAAABMfo/nOTYv4ko22gaCKSfkqtYpn4D__rZvxXBgCLcBGAs/s640/_100816949_995fa22d-57df-4dc4-987a-5b184c28bde8.jpg']", "permalink": "", "publish_date": "20018-04-08T00:00:00+00:145", "keyword": "Trump condemns Syria chemical", "twitter_url": "https://twitter.com/BBCBreaking/status/982974873134825473", "null": ["", "", "", ""]}, {"id": "2146", "claim": "Man dies in Trump Tower blaze", "rating": "TRUE", "image_url": "['http://imbo2.tv2.dk/users/editorial/images/08327611-ec74-4692-84db-21187c0d8291.jpg?publicKey=drupal&t[0]=tv2cropping:width=940,height=529&accessToken=5623778825bd58e520f61f563a92dd043413130a90fc756a57ede2d7fa6ddad8']", "permalink": "", "publish_date": "20018-04-07T00:00:00+00:146", "keyword": "die Trump Tower blaze", "twitter_url": "https://twitter.com/BBCBreaking/status/982756434264907776", "null": ["", "", "", ""]}, {"id": "2147", "claim": "Canadian police say 14 killed as lorry and bus carrying junior ice hockey team collide", "rating": "TRUE", "image_url": "['https://ichef.bbci.co.uk/news/1024/branded_news/1263C/production/_100742357_dzgruvzvoaenwnb.jpg']", "permalink": "", "publish_date": "20018-04-06T00:00:00+00:147", "keyword": "Canada hockey crash kill", "twitter_url": "https://twitter.com/BBCBreaking/status/982511615705800705", "null": ["", "", "", ""]}, {"id": "2148", "claim": "Man, 78, arrested after suspected burglar was fatally stabbed at his London home faces no further action", "rating": "TRUE", "image_url": "['https://i.dailymail.co.uk/i/newpix/2018/04/11/16/4AFA743700000578-5602381-Richard_Osborn_Brooks_78_left_fears_never_being_able_to_return_h-a-13_1523462027795.jpg']", "permalink": "", "publish_date": "20018-04-06T00:00:00+00:148", "keyword": "Osborn-Brooks suspicion murder stabbed", "twitter_url": "https://twitter.com/BBCBreaking/status/982307821365678081", "null": ["", "", "", ""]}, {"id": "2149", "claim": "Ex-spy improving rapidly after poisoning", "rating": "TRUE", "image_url": "['https://ichef.bbci.co.uk/news/936/cpsprodpb/E362/production/_100701285_skripal_comp-1.jpg']", "permalink": "", "publish_date": "20018-04-06T00:00:00+00:149", "keyword": "Skripal improving rapidly poisoning", "twitter_url": "https://twitter.com/BBCBreaking/status/982236303960850435", "null": ["", "", "", ""]}, {"id": "2150", "claim": "Bollywood star Khan jailed for five years.", "rating": "TRUE", "image_url": "['https://pbs.twimg.com/media/DaBpgrTWsAIeYo1.jpg']", "permalink": "", "publish_date": "20018-04-04T00:00:00+00:150", "keyword": "Bollywood Khan jail five", "twitter_url": "https://twitter.com/BBCBreaking/status/981777203678588928", "null": ["", "", "", ""]}, {"id": "2151", "claim": "Former England and Chelsea midfielder Ray Wilkins has died in hospital at the age of 61. ", "rating": "TRUE", "image_url": "['https://metrouk2.files.wordpress.com/2018/03/sei_5406369.jpg?w=620&h=432&crop=1&quality=80']", "permalink": "", "publish_date": "20018-04-04T00:00:00+00:151", "keyword": "Ray Wilkins died 61", "twitter_url": "https://twitter.com/BBCSport/status/981521151221526529", "null": ["", "", "", ""]}, {"id": "2152", "claim": "South African anti-apartheid campaigner Winnie Mandela has died aged 81", "rating": "TRUE", "image_url": "['https://images.sudouest.fr/2018/04/02/5ac23d9766a4bd0b4e80a0dd/widescreen/1000x500/winnie-mandela-est-decedee-des-suites-d-une-longue-maladie.jpg']", "permalink": "", "publish_date": "20018-04-02T00:00:00+00:152", "keyword": "anti-apartheid Winnie Mandela died", "twitter_url": "https://twitter.com/BBCBreaking/status/980808352501559297", "null": ["", "", "", ""]}, {"id": "2153", "claim": "Space lab comes down over South Pacific.", "rating": "TRUE", "image_url": "['https://i.guim.co.uk/img/media/1d050465f7b4b026b10b43d34f360881ef1093a7/0_228_1080_648/master/1080.jpg?w=700&q=55&auto=format&usm=12&fit=max&s=746c5de74e883bf147533b3611e04a5c']", "permalink": "", "publish_date": "20018-04-01T00:00:00+00:153", "keyword": "Tiangong-1 down South Pacific", "twitter_url": "https://twitter.com/BBCBreaking/status/980617803840573440", "null": ["", "", "", ""]}, {"id": "2154", "claim": "Anthony Joshua wins by unanimous decision!", "rating": "TRUE", "image_url": "['https://i.dailymail.co.uk/i/newpix/2018/05/29/11/4CB95F7100000578-0-image-a-6_1527590105287.jpg']", "permalink": "", "publish_date": "20018-03-31T00:00:00+00:154", "keyword": "Anthony Joshua win unanimous", "twitter_url": "https://twitter.com/BBCSport/status/980213793354641408", "null": ["", "", "", ""]}, {"id": "2155", "claim": "Arnold Schwarzenegger undergoes emergency open heart surgery in Los Angeles.", "rating": "TRUE", "image_url": "['https://ichef.bbci.co.uk/news/1024/branded_news/43E7/production/_100638371_hi045568024.jpg']", "permalink": "", "publish_date": "20018-03-30T00:00:00+00:155", "keyword": "Schwarzenegger emergency heart surgery", "twitter_url": "https://twitter.com/BBCSport/status/980213793354641408", "null": ["", "", "", ""]}, {"id": "2156", "claim": "Deadly clashes in Gaza border protest. ", "rating": "TRUE", "image_url": "['https://www.khnsaa.ps/admin-assets/uploads/imgnews/2018/04/09/1107e2565722897b826cbcbe27753b05_400_770.jpg']", "permalink": "", "publish_date": "20018-03-30T00:00:00+00:156", "keyword": "clashes Gaza border protest", "twitter_url": "https://twitter.com/BBCBreaking/status/979685514075955200", "null": ["", "", "", ""]}, {"id": "2157", "claim": "Russia expels US diplomats in tit-for-tat", "rating": "TRUE", "image_url": "['https://ichef.bbci.co.uk/news/660/cpsprodpb/15E67/production/_100630798_fd197f78-5f76-4988-ab0b-4e7303daa9c7.jpg']", "permalink": "", "publish_date": "20018-03-29T00:00:00+00:157", "keyword": "Russia expels US diplomats ", "twitter_url": "https://twitter.com/BBCBreaking/status/979406557682249728", "null": ["", "", "", ""]}, {"id": "2158", "claim": "Spy's front door focus of poisoning probe. ", "rating": "TRUE", "image_url": "['https://i.redditmedia.com/Ho4cKQ1b9AsSAvypQIecVrffIFOwtZaS5OhH0l3LweM.jpg?s=e75f1b20af95a0ba58cf64b1935b6911']", "permalink": "", "publish_date": "20018-03-28T00:00:00+00:158", "keyword": "Segei front poisoning probe", "twitter_url": "https://twitter.com/BBCBreaking/status/979078021821992961", "null": ["", "", "", ""]}, {"id": "2159", "claim": "Triple teen death crash driver jailed", "rating": "TRUE", "image_url": "['https://ichef.bbci.co.uk/news/1024/branded_news/15E09/production/_99790698_hayes_comp_rt.jpg']", "permalink": "", "publish_date": "20018-03-28T00:00:00+00:159", "keyword": "Chudasama jail drive crash", "twitter_url": "https://twitter.com/BBCBreaking/status/978991040123240448", "null": ["", "", "", ""]}, {"id": "2160", "claim": "Jet makes history on flight from Australia.", "rating": "TRUE", "image_url": "['https://media.licdn.com/media-proxy/ext?w=800&h=800&hash=%2BSFgZxyRRra42M%2BT7plqlH%2FWUOg%3D&ora=1%2CaFBCTXdkRmpGL2lvQUFBPQ%2CxAVta5g-0R6nlh8Tw1It6a2FowGz60oISIfYC2G8G2f1spyfNT-tdoDSeLKjoEtOdSkGlhJkcrG-GGGiSp7EfeqlDKIGyfWeQceHQlIpbllko0VL6YYCYRph57KDQLjUJiFc07EJKH2eMp_LRGYHDi4F8PyuAdXUP2wk_3S8fJ2zOtRkaKNjpYYXk2wDrcbnOcwm7qp92nlw7Ey3_vSvZj8m3rymP2uZP1sSLnTSdehDm6me5SCjul3ztmbQiMKXDZuMCYkWnkadsNrzSRar2kpjj2QR1AI3st1QFSLMhYAz7W-aD8YnVRmpscSwWmGK_5JG6QNE']", "permalink": "", "publish_date": "20018-03-24T00:00:00+00:160", "keyword": "non-stop flight UK Australia", "twitter_url": "https://twitter.com/BBCBreaking/status/977760879180767232", "null": ["", "", "", ""]}, {"id": "2161", "claim": "Russia to expel 23 UK diplomats in spy row", "rating": "TRUE", "image_url": "['https://images-news.now.com/newsimage/NewsImage/RUS.UK.2200.1703.jpg']", "permalink": "", "publish_date": "20018-03-17T00:00:00+00:161", "keyword": "Russsia expel UK diplomats ", "twitter_url": "https://twitter.com/BBCBreaking/status/974923590293491712", "null": ["", "", "", ""]}, {"id": "2162", "claim": "Iraqi teenager convicted over Tube bomb", "rating": "TRUE", "image_url": "['https://media2.s-nbcnews.com/i/newscms/2018_11/2365411/180316-ahmed-hassan-1-al-1128_e738023f3cad7dc93d141bb8700d4bb7.jpg']", "permalink": "", "publish_date": "20018-03-16T00:00:00+00:162", "keyword": "Ahmed Hassan murder MarParsons", "twitter_url": "https://twitter.com/BBCBreaking/status/974608654988169216", "null": ["", "", "", ""]}, {"id": "2163", "claim": "Bullseye host Jim Bowen dies at 80.", "rating": "TRUE", "image_url": "['https://cdn.images.dailystar.co.uk/dynamic/117/photos/483000/620x/Jim-Bowen-688811.jpg']", "permalink": "", "publish_date": "20018-03-14T00:00:00+00:163", "keyword": "Bullseye Bowen dies 80", "twitter_url": "https://twitter.com/BBCBreaking/status/973907129588436992", "null": ["", "", "", ""]}, {"id": "2164", "claim": "Stephen Hawking died at age 76.", "rating": "TRUE", "image_url": "['http://kalampati.com/eximages/Thumbnails1_stephan_hawking_AJvLt33f1c.jpg']", "permalink": "", "publish_date": "20018-03-13T00:00:00+00:164", "keyword": "Stephen Hawking died 76", "twitter_url": "https://twitter.com/BBCBreaking/status/973774263013519360", "null": ["", "", "", ""]}, {"id": "2165", "claim": "Comedy legend Sir Ken Dodd dies, aged 90.", "rating": "TRUE", "image_url": "['https://i.guim.co.uk/img/media/32c3c0ae1f168a1a305a32e55ad56699ed582c30/0_0_3500_2064/master/3500.jpg?w=700&q=55&auto=format&usm=12&fit=max&s=0084470d9bc1ba7c1ea90b51fa25d7d1']", "permalink": "", "publish_date": "20018-03-11T00:00:00+00:165", "keyword": "Ken Dodd dies 90", "twitter_url": "https://twitter.com/BBCBreaking/status/973010283991101442", "null": ["", "", "", ""]}, {"id": "2166", "claim": "Key Trump economy adviser Cohn resigns.", "rating": "TRUE", "image_url": "['https://kriptopolo.com/wp-content/uploads/2018/05/gary-cogn-702x336.jpg']", "permalink": "", "publish_date": "20018-03-06T00:00:00+00:166", "keyword": "key economy Cohn resigns", "twitter_url": "https://twitter.com/BBCBreaking/status/971152924985487368", "null": ["", "", "", ""]}, {"id": "2167", "claim": "Sir Bradley Wiggins says he '100% did not cheat' after damning MPs' report", "rating": "TRUE", "image_url": "['https://static.standard.co.uk/s3fs-public/thumbnails/image/2018/03/06/15/wiggins0603abcd.jpg']", "permalink": "", "publish_date": "20018-03-05T00:00:00+00:167", "keyword": "Bradley Wiggins not cheat ", "twitter_url": "https://twitter.com/BBCBreaking/status/970725256116756481", "null": ["", "", "", ""]}, {"id": "2168", "claim": "Critically ill man is former Russian spy. ", "rating": "TRUE", "image_url": "['https://cdn.images.express.co.uk/img/dynamic/1/590x/Maltings-Salisbury-927354.jpg']", "permalink": "", "publish_date": "20018-03-05T00:00:00+00:168", "keyword": "Salisbury Russian spy exposure", "twitter_url": "https://twitter.com/BBCBreaking/status/970720887505907713", "null": ["", "", "", ""]}, {"id": "2169", "claim": "Sir Roger Bannister dies at 88", "rating": "TRUE", "image_url": "['https://i.guim.co.uk/img/media/d381d0c7e04fdf415ff3b03e7b62597bd2bd2b31/0_0_1569_2121/master/1569.jpg?w=700&q=55&auto=format&usm=12&fit=max&s=683b210f2f0b5cd047a83e8cea1c6635']", "permalink": "", "publish_date": "20018-03-04T00:00:00+00:169", "keyword": "Roger Bannister dies 88", "twitter_url": "https://twitter.com/BBCBreaking/status/970259792060207104", "null": ["", "", "", ""]}, {"id": "2170", "claim": "Man shoots himself outside White House", "rating": "TRUE", "image_url": "['https://i.pinimg.com/originals/e4/2f/8f/e42f8f4b3c14a37e76ab9fab6c366984.jpg']", "permalink": "", "publish_date": "20018-03-03T00:00:00+00:170", "keyword": "shoot himself outside White", "twitter_url": "https://twitter.com/BBCBreaking/status/969984929961512960", "null": ["", "", "", ""]}, {"id": "2171", "claim": "Royal wedding: Windsor Castle invitation for public", "rating": "TRUE", "image_url": "['https://www.gossipcop.com/wp-content/uploads/2018/04/Prince-Harry-Meghan-Markle-Honeymoon.jpg']", "permalink": "", "publish_date": "20018-03-02T00:00:00+00:171", "keyword": "Royal wedding invitation public", "twitter_url": "https://twitter.com/BBCBreaking/status/969504728089530369", "null": ["", "", "", ""]}, {"id": "2172", "claim": "Kushner loses top-level security clearance", "rating": "TRUE", "image_url": "['https://uc.udn.com.tw/photo/2018/02/28/6/4529531.jpg']", "permalink": "", "publish_date": "20018-02-27T00:00:00+00:172", "keyword": "Kushner lose top-level security", "twitter_url": "https://twitter.com/BBCBreaking/status/968591163077914628", "null": ["", "", "", ""]}, {"id": "2173", "claim": "Vicar of Dibley actress Emma Chambers dies aged 53", "rating": "TRUE", "image_url": "['https://1.bp.blogspot.com/-ZTZVihU-_ws/WpGigd0gXUI/AAAAAAAAxM8/rywMsZgI7bU3kGvBgBO0GEqgXL0AMtWLgCLcBGAs/s1600/emma-chambers.jpg']", "permalink": "", "publish_date": "20018-02-T00:00:00+00:173", "keyword": "Emma Chambers dies 53", "twitter_url": "https://twitter.com/BBCBreaking/status/967434947320479745", "null": ["", "", "", ""]}, {"id": "2174", "claim": "Influential US preacher Billy Graham dies. ", "rating": "TRUE", "image_url": "['https://ichef.bbci.co.uk/images/ic/1920x1080/p05z9kn8.jpg ']", "permalink": "", "publish_date": "20018-02-21T00:00:00+00:174", "keyword": "US Billy Graham dies", "twitter_url": "https://twitter.com/BBCBreaking/status/966302228817510400", "null": ["", "", "", ""]}, {"id": "2175", "claim": "Elise Christie is out of the WinterOlympics. ", "rating": "TRUE", "image_url": "['https://www.thetimes.co.uk/imageserver/image/methode%2Ftimes%2Fprod%2Fweb%2Fbin%2F8ea6e5ea-17d0-11e8-a427-78e8af199a96.jpg?crop=3063%2C2042%2C77%2C51']", "permalink": "", "publish_date": "20018-02-20T00:00:00+00:175", "keyword": "Elise Christie out WinterOlympics", "twitter_url": "https://twitter.com/BBCSport/status/965894569375170561", "null": ["", "", "", ""]}, {"id": "2176", "claim": "Barry Bennell sentenced to 31 years for 50 counts of child sexual abuse", "rating": "TRUE", "image_url": "['https://ichef.bbci.co.uk/news/1024/branded_news/12CE5/production/_100092077_de27-1.jpg']", "permalink": "", "publish_date": "20018-02-19T00:00:00+00:176", "keyword": "Bennell sentenced  child sexual ", "twitter_url": "https://twitter.com/BBCBreaking/status/965601261616881664", "null": ["", "", "", ""]}, {"id": "2177", "claim": "Trump attacks FBI over school shooting.", "rating": "TRUE", "image_url": "['https://ravenfirearmstraining.files.wordpress.com/2018/02/parkland-shooting-1.jpg?w=400&h=200&crop=1']", "permalink": "", "publish_date": "20018-02-17T00:00:00+00:177", "keyword": "Trump attack FBI shooting", "twitter_url": "https://twitter.com/BBCBreaking/status/965081563951190016", "null": ["", "", "", ""]}, {"id": "2178", "claim": "Henry Bolton sacked as UKIP leader.", "rating": "TRUE", "image_url": "['https://ichef.bbci.co.uk/images/ic/1024x576/p05yj7vk.jpg']", "permalink": "", "publish_date": "20018-02-17T00:00:00+00:178", "keyword": "Henry Bolton sacked UKIP", "twitter_url": "https://twitter.com/BBCBreaking/status/964902810486747141", "null": ["", "", "", ""]}, {"id": "2179", "claim": "Zainab's killer gets four death sentences. ", "rating": "TRUE", "image_url": "['https://ichef.bbci.co.uk/news/624/cpsprodpb/CBE6/production/_100889125_3dab1dc3-266b-429f-836f-f6db35d38df9.jpg']", "permalink": "", "publish_date": "20018-02-17T00:00:00+00:179", "keyword": "Zainab's killer four sentences", "twitter_url": "https://twitter.com/BBCBreaking/status/964780447782920192", "null": ["", "", "", ""]}, {"id": "2180", "claim": "Elise Christie has crashed out of the women's 1500m short track semi-finals. ", "rating": "TRUE", "image_url": "['https://pbs.twimg.com/media/DWO_NGSWkAANU7F.jpg']", "permalink": "", "publish_date": "20018-02-17T00:00:00+00:180", "keyword": "Christie out 1500m semi-finals", "twitter_url": "https://twitter.com/BBCSport/status/964825005266821120", "null": ["", "", "", ""]}, {"id": "2181", "claim": "At least 17 dead in US school shooting.", "rating": "TRUE", "image_url": "['https://i1.wp.com/chaosrift.com/wp-content/uploads/2018/06/p05y7j42.jpg?fit=720%2C405&ssl=1&resize=350%2C200']", "permalink": "", "publish_date": "20018-02-15T00:00:00+00:181", "keyword": "Nikolas Cruz school shooting", "twitter_url": "https://twitter.com/BBCBreaking/status/964112892898545667", "null": ["", "", "", ""]}, {"id": "2182", "claim": "Toronto's Danforth community unites at vigil after shooting. ", "rating": "TRUE", "image_url": "['https://shawglobalnews.files.wordpress.com/2018/07/19475150.jpg?quality=70']", "permalink": "", "publish_date": "20018-07-29T00:00:00+00:182", "keyword": "Danforth unites vigil shooting", "twitter_url": "https://twitter.com/CBCAlerts/status/1023669005696020480", "null": ["", "", "", ""]}, {"id": "2183", "claim": "Active shooter reported at Texas border town shopping mall", "rating": "TRUE", "image_url": "['https://i.pinimg.com/736x/18/71/17/1871179555aca31281b17fc72ae0a2e4.jpg']", "permalink": "", "publish_date": "20018-07-28T00:00:00+00:183", "keyword": "shooter Texas border mall", "twitter_url": "https://twitter.com/FoxNews/status/1023269595854110720", "null": ["", "", "", ""]}, {"id": "2184", "claim": "An Air Force C-17 containing the remains of fallen U.S. servicemembers has departed Wonsan", "rating": "TRUE", "image_url": "['https://media.nu.nl/m/b7sxwamat8m4_wd1280.jpg/noord-korea-stelt-denuclearisatie-wankelt-eenzijdige-eisen-van-vs.jpg']", "permalink": "", "publish_date": "20018-07-26T00:00:00+00:184", "keyword": "C-17 servicemembers departed Wonsan", "twitter_url": "https://twitter.com/starsandstripes/status/1022670545337241600", "null": ["", "", "", ""]}, {"id": "2185", "claim": "Theresa May takes formal charge of the negotiations.", "rating": "TRUE", "image_url": "['https://s13.stc.all.kpcdn.net/share/i/12/10548593/inx960x640.jpg']", "permalink": "", "publish_date": "20018-07-26T00:00:00+00:185", "keyword": "Theresa May charge negotiations", "twitter_url": "https://twitter.com/GetBritainOut/status/1021766832766808065", "null": ["", "", "", ""]}, {"id": "2186", "claim": "Cohen willing to tell Mueller that Trump knew of 2016 Russia meeting", "rating": "TRUE", "image_url": "['https://media.licdn.com/media-proxy/ext?w=800&h=800&hash=TA%2Bn%2B1J4YNRCtJ2KgivjTiFeLNc%3D&ora=1%2CaFBCTXdkRmpGL2lvQUFBPQ%2CxAVta5g-0R69hAxUxAhv46GM4nCP61VOQoPRCy_iDmfso4bVfy60KJCKZvSjuwRLKXtU0xtwLqi3GHSlUoa_Wp_tC8lz_dene8T5cxcWJBU7hG5KocM-OB1qs4DoBuT9JXxohe1baXa5Z7ykMFdvD2hmrOnRYIbefQVciA_cSYmxSskWDLY2r5JV1kxWopDLEdIqhYN6zWZu2l-s9P_8PyxR-JaqB0rzA1kiBCPXMfhStvLegmI']", "permalink": "", "publish_date": "20018-07-26T00:00:00+00:186", "keyword": "Cohen Mueller 2016 Russia", "twitter_url": "https://twitter.com/BreakingNews/status/1022686214460080130", "null": ["", "", "", ""]}, {"id": "2187", "claim": "White House bans network pool reporter from Rose Garden event", "rating": "TRUE", "image_url": "['https://cdn1.thr.com/sites/default/files/imagecache/NFE_Landscape/2018/07/kaitlan_collins.jpg']", "permalink": "", "publish_date": "20018-07-25T00:00:00+00:187", "keyword": "White bans reporter Rose", "twitter_url": "https://twitter.com/BreakingNews/status/1022252702212997121", "null": ["", "", "", ""]}, {"id": "2188", "claim": "Hackers break into voting machines within 2 hours at Defcon", "rating": "TRUE", "image_url": "['https://amp.businessinsider.com/images/597f871f4528e6a8038b4f38-1136-852.jpg']", "permalink": "", "publish_date": "20018-07-29T00:00:00+00:188", "keyword": "Hackers voting machines Defcon", "twitter_url": "https://twitter.com/IlvesToomas/status/1023665011221090304", "null": ["", "", "", ""]}, {"id": "2189", "claim": "Three new polls show bad news for Republicans ahead of the midterm elections ", "rating": "TRUE", "image_url": "['https://i.ytimg.com/vi/n9Ah0iJaTrU/maxresdefault.jpg']", "permalink": "", "publish_date": "20018-07-29T00:00:00+00:189", "keyword": "", "twitter_url": "https://twitter.com/CNN/status/1023565328406794240", "null": ["", "", "", ""]}, {"id": "2190", "claim": "Ex-Tory MP dismisses 'Dark Money' claims.", "rating": "TRUE", "image_url": "['http://www.in-formsolutions.com/media/1092/plics.jpg?anchor=center&mode=crop&width=498&height=268&rnd=131726813060000000']", "permalink": "", "publish_date": "20018-07-29T00:00:00+00:190", "keyword": "polls bad Republicans ahead", "twitter_url": "https://twitter.com/SaorAlba59/status/1023574386899603456", "null": ["", "", "", ""]}, {"id": "2191", "claim": "The Government plans to extend BlueBadge permit criteria specifically for 'hidden disabilities'.", "rating": "TRUE", "image_url": "['https://i1.wp.com/newsfaltu.com/wp-content/uploads/2018/07/_102732766_gettyimages-930222910.jpg?resize=660%2C330']", "permalink": "", "publish_date": "20018-07-T00:00:00+00:191", "keyword": "extend BlueBadge permit disabilities", "twitter_url": "https://twitter.com/CrohnsColitisUK/status/1023495072044724224", "null": ["", "", "", ""]}, {"id": "2192", "claim": "Defrauded Student Borrowers Must Prove Intent; Sessions Calls Students 'Snowflakes'", "rating": "TRUE", "image_url": "['https://static01.nyt.com/images/2018/07/24/us/25xp-alabama/25xp-alabama-videoLarge.jpg']", "permalink": "", "publish_date": "20018-07-28T00:00:00+00:192", "keyword": "Borrowers Prove Intent  Snowflakes", "twitter_url": "https://twitter.com/NPR/status/1023376309668331520", "null": ["", "", "", ""]}, {"id": "2193", "claim": "'Police can no longer handle the lawless jungle after dark in Amsterdam¡¯", "rating": "TRUE", "image_url": "['http://en.el-balad.com/upload/photo/news/238/9/300x169o/122.jpg?q=1']", "permalink": "", "publish_date": "20018-07-28T00:00:00+00:193", "keyword": "Police handle jungle Amsterdam", "twitter_url": "https://twitter.com/RT_com/status/1023236648325263360", "null": ["", "", "", ""]}, {"id": "2194", "claim": "Lee Lin Chin's message to fans on her last day", "rating": "TRUE", "image_url": "['https://i1.wp.com/yakatuon.com/wp-content/uploads/2016/08/screen-shot-2016-08-22-at-10-19-02-am.png?resize=690%2C395&ssl=1']", "permalink": "", "publish_date": "20018-07-29T00:00:00+00:194", "keyword": "Lin Chin's message last ", "twitter_url": "https://twitter.com/SBSNews/status/1023481832824696832", "null": ["", "", "", ""]}, {"id": "2195", "claim": "By 2050 humans will attend own funerals as robots", "rating": "TRUE", "image_url": "['http://www.eldawlagia.com/temp/resized/medium_2018-07-26-88882b6277.jpg']", "permalink": "", "publish_date": "20018-07-29T00:00:00+00:195", "keyword": "2050 sattend funerals robot", "twitter_url": "https://twitter.com/RTUKnews/status/1023645332586954752", "null": ["", "", "", ""]}, {"id": "2196", "claim": "'Flaming feminist' Ruth Bader Ginsburg wants five more years", "rating": "TRUE", "image_url": "['https://wtop.com/wp-content/uploads/2018/07/Israel_People_Ginsburg_76953-780x520.jpg']", "permalink": "", "publish_date": "20018-07-29T00:00:00+00:196", "keyword": "Bader Ginsburg wants five", "twitter_url": "https://twitter.com/guardian/status/1023743683097776136", "null": ["", "", "", ""]}, {"id": "2197", "claim": "UK government urged to halt plans to expand compulsory voter ID", "rating": "TRUE", "image_url": "['https://i.guim.co.uk/img/media/633add0bb836bec5fcab37626824c31c10ce825e/0_134_3500_2101/500.jpg?q=55&auto=format&usm=12&fit=max&s=44a53f600cb2f799eb226ca2b1c91b7d']", "permalink": "", "publish_date": "20018-07-T00:00:00+00:197", "keyword": "UK halt expand voter", "twitter_url": "https://twitter.com/guardian/status/1023713377061875712", "null": ["", "", "", ""]}, {"id": "2198", "claim": "Rightwing UK thinktank 'offered ministerial access' to potential US donors", "rating": "TRUE", "image_url": "['https://i.guim.co.uk/img/media/1e7d333e2324388b427f006e7aa1d750d93e69d1/0_213_4928_2957/master/4928.jpg?w=1200&h=630&q=55&auto=format&usm=12&fit=crop&crop=faces%2Centropy&bm=normal&ba=bottom%2Cleft&blend64=aHR0cHM6Ly91cGxvYWRzLmd1aW0uY28udWsvMjAxOC8wMS8zMS90d2l0dGVyX2RlZmF1bHQucG5n&s=f7590da78db8dd9d6016aa3a3edc67a9']", "permalink": "", "publish_date": "20018-07-29T00:00:00+00:198", "keyword": "UK ministerial US donors", "twitter_url": "https://twitter.com/guardian/status/1023630355058880513", "null": ["", "", "", ""]}, {"id": "2199", "claim": "Giuliani: 180 tapes seized from Cohen but Trump only speaks on one", "rating": "TRUE", "image_url": "['https://i.guim.co.uk/img/media/a0ef71188612a8102feba92c027e7b7308c12c9c/0_71_3500_2100/master/3500.jpg?w=1200&h=630&q=55&auto=format&usm=12&fit=crop&crop=faces%2Centropy&bm=normal&ba=bottom%2Cleft&blend64=aHR0cHM6Ly9hc3NldHMuZ3VpbS5jby51ay9pbWFnZXMvb3ZlcmxheXMvZDM1ODZhNWVmNTc4MTc1NmQyMWEzYjYzNWU1MTcxNDEvdGctZGVmYXVsdC5wbmc=&s=173614c87cf0f3b474f681d5bf9eb6c2']", "permalink": "", "publish_date": "20018-07-29T00:00:00+00:199", "keyword": "Giuliani tapes seizedCohen ", "twitter_url": "https://twitter.com/guardian/status/1023619952127950848", "null": ["", "", "", ""]}]